{
  "channel": {
    "title": "XML Historical Foreign Exchange Rates for Mauritian Rupee (MUR) (13 Apr 2018)",
    "link": "http://www.floatrates.com/currency/mur/",
    "xmlLink": "http://www.floatrates.com/daily/mur.xml",
    "description": "XML historical foreign exchange rates for Mauritian Rupee (MUR) from the Float Rates. Published at 13 Apr 2018.",
    "language": "en",
    "baseCurrency": "MUR",
    "pubDate": "Fri, 13 Apr 2018",
    "lastBuildDate": "Fri, 13 Apr 2018",
    "item": [
      {
        "title": "1 MUR = 0.029732 USD",
        "link": "http://www.floatrates.com/mur/usd/",
        "description": "1 Mauritian Rupee = 0.029732 U.S. Dollar",
        "pubDate": null,
        "baseCurrency": "MUR",
        "baseName": "Mauritian Rupee",
        "targetCurrency": "USD",
        "targetName": "U.S. Dollar",
        "exchangeRate": "0.029732",
        "inverseRate": "33.633811",
        "inverseDescription": "1 U.S. Dollar = 33.633811 Mauritian Rupee"
      },
      {
        "title": "1 MUR = 0.927158 NIO",
        "link": "http://www.floatrates.com/mur/nio/",
        "description": "1 Mauritian Rupee = 0.927158 Nicaraguan C\u00f3rdoba",
        "pubDate": null,
        "baseCurrency": "MUR",
        "baseName": "Mauritian Rupee",
        "targetCurrency": "NIO",
        "targetName": "Nicaraguan C\u00f3rdoba",
        "exchangeRate": "0.927158",
        "inverseRate": "1.078564",
        "inverseDescription": "1 Nicaraguan C\u00f3rdoba = 1.078564 Mauritian Rupee"
      },
      {
        "title": "1 MUR = 0.186821 CNY",
        "link": "http://www.floatrates.com/mur/cny/",
        "description": "1 Mauritian Rupee = 0.186821 Chinese Yuan",
        "pubDate": null,
        "baseCurrency": "MUR",
        "baseName": "Mauritian Rupee",
        "targetCurrency": "CNY",
        "targetName": "Chinese Yuan",
        "exchangeRate": "0.186821",
        "inverseRate": "5.352724",
        "inverseDescription": "1 Chinese Yuan = 5.352724 Mauritian Rupee"
      },
      {
        "title": "1 MUR = 3.196378 JPY",
        "link": "http://www.floatrates.com/mur/jpy/",
        "description": "1 Mauritian Rupee = 3.196378 Japanese Yen",
        "pubDate": null,
        "baseCurrency": "MUR",
        "baseName": "Mauritian Rupee",
        "targetCurrency": "JPY",
        "targetName": "Japanese Yen",
        "exchangeRate": "3.196378",
        "inverseRate": "0.312854",
        "inverseDescription": "1 Japanese Yen = 0.312854 Mauritian Rupee"
      },
      {
        "title": "1 MUR = 0.024122 EUR",
        "link": "http://www.floatrates.com/mur/eur/",
        "description": "1 Mauritian Rupee = 0.024122 Euro",
        "pubDate": null,
        "baseCurrency": "MUR",
        "baseName": "Mauritian Rupee",
        "targetCurrency": "EUR",
        "targetName": "Euro",
        "exchangeRate": "0.024122",
        "inverseRate": "41.455276",
        "inverseDescription": "1 Euro = 41.455276 Mauritian Rupee"
      },
      {
        "title": "1 MUR = 31.807359 KRW",
        "link": "http://www.floatrates.com/mur/krw/",
        "description": "1 Mauritian Rupee = 31.807359 South Korean Won",
        "pubDate": null,
        "baseCurrency": "MUR",
        "baseName": "Mauritian Rupee",
        "targetCurrency": "KRW",
        "targetName": "South Korean Won",
        "exchangeRate": "31.807359",
        "inverseRate": "0.031439",
        "inverseDescription": "1 South Korean Won = 0.031439 Mauritian Rupee"
      },
      {
        "title": "1 MUR = 0.038996 SGD",
        "link": "http://www.floatrates.com/mur/sgd/",
        "description": "1 Mauritian Rupee = 0.038996 Singapore Dollar",
        "pubDate": null,
        "baseCurrency": "MUR",
        "baseName": "Mauritian Rupee",
        "targetCurrency": "SGD",
        "targetName": "Singapore Dollar",
        "exchangeRate": "0.038996",
        "inverseRate": "25.643418",
        "inverseDescription": "1 Singapore Dollar = 25.643418 Mauritian Rupee"
      },
      {
        "title": "1 MUR = 0.040338 NZD",
        "link": "http://www.floatrates.com/mur/nzd/",
        "description": "1 Mauritian Rupee = 0.040338 New Zealand Dollar",
        "pubDate": null,
        "baseCurrency": "MUR",
        "baseName": "Mauritian Rupee",
        "targetCurrency": "NZD",
        "targetName": "New Zealand Dollar",
        "exchangeRate": "0.040338",
        "inverseRate": "24.790427",
        "inverseDescription": "1 New Zealand Dollar = 24.790427 Mauritian Rupee"
      },
      {
        "title": "1 MUR = 0.020848 GBP",
        "link": "http://www.floatrates.com/mur/gbp/",
        "description": "1 Mauritian Rupee = 0.020848 U.K. Pound Sterling",
        "pubDate": null,
        "baseCurrency": "MUR",
        "baseName": "Mauritian Rupee",
        "targetCurrency": "GBP",
        "targetName": "U.K. Pound Sterling",
        "exchangeRate": "0.020848",
        "inverseRate": "47.966696",
        "inverseDescription": "1 U.K. Pound Sterling = 47.966696 Mauritian Rupee"
      },
      {
        "title": "1 MUR = 0.115315 MYR",
        "link": "http://www.floatrates.com/mur/myr/",
        "description": "1 Mauritian Rupee = 0.115315 Malaysian Ringgit",
        "pubDate": null,
        "baseCurrency": "MUR",
        "baseName": "Mauritian Rupee",
        "targetCurrency": "MYR",
        "targetName": "Malaysian Ringgit",
        "exchangeRate": "0.115315",
        "inverseRate": "8.671914",
        "inverseDescription": "1 Malaysian Ringgit = 8.671914 Mauritian Rupee"
      },
      {
        "title": "1 MUR = 0.926959 THB",
        "link": "http://www.floatrates.com/mur/thb/",
        "description": "1 Mauritian Rupee = 0.926959 Thai Baht",
        "pubDate": null,
        "baseCurrency": "MUR",
        "baseName": "Mauritian Rupee",
        "targetCurrency": "THB",
        "targetName": "Thai Baht",
        "exchangeRate": "0.926959",
        "inverseRate": "1.078797",
        "inverseDescription": "1 Thai Baht = 1.078797 Mauritian Rupee"
      },
      {
        "title": "1 MUR = 408.454953 IDR",
        "link": "http://www.floatrates.com/mur/idr/",
        "description": "1 Mauritian Rupee = 408.454953 Indonesian Rupiah",
        "pubDate": null,
        "baseCurrency": "MUR",
        "baseName": "Mauritian Rupee",
        "targetCurrency": "IDR",
        "targetName": "Indonesian Rupiah",
        "exchangeRate": "408.454953",
        "inverseRate": "0.002448",
        "inverseDescription": "1 Indonesian Rupiah = 0.002448 Mauritian Rupee"
      },
      {
        "title": "1 MUR = 1.939600 INR",
        "link": "http://www.floatrates.com/mur/inr/",
        "description": "1 Mauritian Rupee = 1.939600 Indian Rupee",
        "pubDate": null,
        "baseCurrency": "MUR",
        "baseName": "Mauritian Rupee",
        "targetCurrency": "INR",
        "targetName": "Indian Rupee",
        "exchangeRate": "1.939600",
        "inverseRate": "0.515570",
        "inverseDescription": "1 Indian Rupee = 0.515570 Mauritian Rupee"
      },
      {
        "title": "1 MUR = 0.871861 TWD",
        "link": "http://www.floatrates.com/mur/twd/",
        "description": "1 Mauritian Rupee = 0.871861 New Taiwan Dollar",
        "pubDate": null,
        "baseCurrency": "MUR",
        "baseName": "Mauritian Rupee",
        "targetCurrency": "TWD",
        "targetName": "New Taiwan Dollar",
        "exchangeRate": "0.871861",
        "inverseRate": "1.146972",
        "inverseDescription": "1 New Taiwan Dollar  = 1.146972 Mauritian Rupee"
      },
      {
        "title": "1 MUR = 679.151779 VND",
        "link": "http://www.floatrates.com/mur/vnd/",
        "description": "1 Mauritian Rupee = 679.151779 Vietnamese Dong",
        "pubDate": null,
        "baseCurrency": "MUR",
        "baseName": "Mauritian Rupee",
        "targetCurrency": "VND",
        "targetName": "Vietnamese Dong",
        "exchangeRate": "679.151779",
        "inverseRate": "0.001472",
        "inverseDescription": "1 Vietnamese Dong = 0.001472 Mauritian Rupee"
      },
      {
        "title": "1 MUR = 0.233393 HKD",
        "link": "http://www.floatrates.com/mur/hkd/",
        "description": "1 Mauritian Rupee = 0.233393 Hong Kong Dollar",
        "pubDate": null,
        "baseCurrency": "MUR",
        "baseName": "Mauritian Rupee",
        "targetCurrency": "HKD",
        "targetName": "Hong Kong Dollar",
        "exchangeRate": "0.233393",
        "inverseRate": "4.284626",
        "inverseDescription": "1 Hong Kong Dollar = 4.284626 Mauritian Rupee"
      },
      {
        "title": "1 MUR = 0.096693 PGK",
        "link": "http://www.floatrates.com/mur/pgk/",
        "description": "1 Mauritian Rupee = 0.096693 Papua New Guinean kina",
        "pubDate": null,
        "baseCurrency": "MUR",
        "baseName": "Mauritian Rupee",
        "targetCurrency": "PGK",
        "targetName": "Papua New Guinean kina",
        "exchangeRate": "0.096693",
        "inverseRate": "10.341966",
        "inverseDescription": "1 Papua New Guinean kina = 10.341966 Mauritian Rupee"
      },
      {
        "title": "1 MUR = 0.028610 CHF",
        "link": "http://www.floatrates.com/mur/chf/",
        "description": "1 Mauritian Rupee = 0.028610 Swiss Franc",
        "pubDate": null,
        "baseCurrency": "MUR",
        "baseName": "Mauritian Rupee",
        "targetCurrency": "CHF",
        "targetName": "Swiss Franc",
        "exchangeRate": "0.028610",
        "inverseRate": "34.952249",
        "inverseDescription": "1 Swiss Franc = 34.952249 Mauritian Rupee"
      },
      {
        "title": "1 MUR = 0.109192 AED",
        "link": "http://www.floatrates.com/mur/aed/",
        "description": "1 Mauritian Rupee = 0.109192 U.A.E Dirham",
        "pubDate": null,
        "baseCurrency": "MUR",
        "baseName": "Mauritian Rupee",
        "targetCurrency": "AED",
        "targetName": "U.A.E Dirham",
        "exchangeRate": "0.109192",
        "inverseRate": "9.158201",
        "inverseDescription": "1 U.A.E Dirham = 9.158201 Mauritian Rupee"
      },
      {
        "title": "1 MUR = 0.037655 CAD",
        "link": "http://www.floatrates.com/mur/cad/",
        "description": "1 Mauritian Rupee = 0.037655 Canadian Dollar",
        "pubDate": null,
        "baseCurrency": "MUR",
        "baseName": "Mauritian Rupee",
        "targetCurrency": "CAD",
        "targetName": "Canadian Dollar",
        "exchangeRate": "0.037655",
        "inverseRate": "26.557246",
        "inverseDescription": "1 Canadian Dollar = 26.557246 Mauritian Rupee"
      },
      {
        "title": "1 MUR = 0.038206 AUD",
        "link": "http://www.floatrates.com/mur/aud/",
        "description": "1 Mauritian Rupee = 0.038206 Australian Dollar",
        "pubDate": null,
        "baseCurrency": "MUR",
        "baseName": "Mauritian Rupee",
        "targetCurrency": "AUD",
        "targetName": "Australian Dollar",
        "exchangeRate": "0.038206",
        "inverseRate": "26.173692",
        "inverseDescription": "1 Australian Dollar = 26.173692 Mauritian Rupee"
      },
      {
        "title": "1 MUR = 0.050617 AZN",
        "link": "http://www.floatrates.com/mur/azn/",
        "description": "1 Mauritian Rupee = 0.050617 Azerbaijan Manat",
        "pubDate": null,
        "baseCurrency": "MUR",
        "baseName": "Mauritian Rupee",
        "targetCurrency": "AZN",
        "targetName": "Azerbaijan Manat",
        "exchangeRate": "0.050617",
        "inverseRate": "19.756257",
        "inverseDescription": "1 Azerbaijan Manat = 19.756257 Mauritian Rupee"
      },
      {
        "title": "1 MUR = 14.355475 AMD",
        "link": "http://www.floatrates.com/mur/amd/",
        "description": "1 Mauritian Rupee = 14.355475 Armenia Dram",
        "pubDate": null,
        "baseCurrency": "MUR",
        "baseName": "Mauritian Rupee",
        "targetCurrency": "AMD",
        "targetName": "Armenia Dram",
        "exchangeRate": "14.355475",
        "inverseRate": "0.069660",
        "inverseDescription": "1 Armenia Dram = 0.069660 Mauritian Rupee"
      },
      {
        "title": "1 MUR = 0.060782 BYN",
        "link": "http://www.floatrates.com/mur/byn/",
        "description": "1 Mauritian Rupee = 0.060782 Belarussian Ruble",
        "pubDate": null,
        "baseCurrency": "MUR",
        "baseName": "Mauritian Rupee",
        "targetCurrency": "BYN",
        "targetName": "Belarussian Ruble",
        "exchangeRate": "0.060782",
        "inverseRate": "16.452139",
        "inverseDescription": "1 Belarussian Ruble = 16.452139 Mauritian Rupee"
      },
      {
        "title": "1 MUR = 0.047198 BGN",
        "link": "http://www.floatrates.com/mur/bgn/",
        "description": "1 Mauritian Rupee = 0.047198 Bulgarian Lev",
        "pubDate": null,
        "baseCurrency": "MUR",
        "baseName": "Mauritian Rupee",
        "targetCurrency": "BGN",
        "targetName": "Bulgarian Lev",
        "exchangeRate": "0.047198",
        "inverseRate": "21.187560",
        "inverseDescription": "1 Bulgarian Lev = 21.187560 Mauritian Rupee"
      },
      {
        "title": "1 MUR = 0.101440 BRL",
        "link": "http://www.floatrates.com/mur/brl/",
        "description": "1 Mauritian Rupee = 0.101440 Brazilian Real",
        "pubDate": null,
        "baseCurrency": "MUR",
        "baseName": "Mauritian Rupee",
        "targetCurrency": "BRL",
        "targetName": "Brazilian Real",
        "exchangeRate": "0.101440",
        "inverseRate": "9.858023",
        "inverseDescription": "1 Brazilian Real = 9.858023 Mauritian Rupee"
      },
      {
        "title": "1 MUR = 7.501136 HUF",
        "link": "http://www.floatrates.com/mur/huf/",
        "description": "1 Mauritian Rupee = 7.501136 Hungarian Forint",
        "pubDate": null,
        "baseCurrency": "MUR",
        "baseName": "Mauritian Rupee",
        "targetCurrency": "HUF",
        "targetName": "Hungarian Forint",
        "exchangeRate": "7.501136",
        "inverseRate": "0.133313",
        "inverseDescription": "1 Hungarian Forint = 0.133313 Mauritian Rupee"
      },
      {
        "title": "1 MUR = 0.179724 DKK",
        "link": "http://www.floatrates.com/mur/dkk/",
        "description": "1 Mauritian Rupee = 0.179724 Danish Krone",
        "pubDate": null,
        "baseCurrency": "MUR",
        "baseName": "Mauritian Rupee",
        "targetCurrency": "DKK",
        "targetName": "Danish Krone",
        "exchangeRate": "0.179724",
        "inverseRate": "5.564097",
        "inverseDescription": "1 Danish Krone = 5.564097 Mauritian Rupee"
      },
      {
        "title": "1 MUR = 9.735845 KZT",
        "link": "http://www.floatrates.com/mur/kzt/",
        "description": "1 Mauritian Rupee = 9.735845 Kazakhstani Tenge",
        "pubDate": null,
        "baseCurrency": "MUR",
        "baseName": "Mauritian Rupee",
        "targetCurrency": "KZT",
        "targetName": "Kazakhstani Tenge",
        "exchangeRate": "9.735845",
        "inverseRate": "0.102713",
        "inverseDescription": "1 Kazakhstani Tenge = 0.102713 Mauritian Rupee"
      },
      {
        "title": "1 MUR = 2.040306 KGS",
        "link": "http://www.floatrates.com/mur/kgs/",
        "description": "1 Mauritian Rupee = 2.040306 Kyrgyzstan Som",
        "pubDate": null,
        "baseCurrency": "MUR",
        "baseName": "Mauritian Rupee",
        "targetCurrency": "KGS",
        "targetName": "Kyrgyzstan Som",
        "exchangeRate": "2.040306",
        "inverseRate": "0.490123",
        "inverseDescription": "1 Kyrgyzstan Som = 0.490123 Mauritian Rupee"
      },
      {
        "title": "1 MUR = 0.487080 MDL",
        "link": "http://www.floatrates.com/mur/mdl/",
        "description": "1 Mauritian Rupee = 0.487080 Moldova Lei",
        "pubDate": null,
        "baseCurrency": "MUR",
        "baseName": "Mauritian Rupee",
        "targetCurrency": "MDL",
        "targetName": "Moldova Lei",
        "exchangeRate": "0.487080",
        "inverseRate": "2.053050",
        "inverseDescription": "1 Moldova Lei = 2.053050 Mauritian Rupee"
      },
      {
        "title": "1 MUR = 0.103906 TMT",
        "link": "http://www.floatrates.com/mur/tmt/",
        "description": "1 Mauritian Rupee = 0.103906 New Turkmenistan Manat",
        "pubDate": null,
        "baseCurrency": "MUR",
        "baseName": "Mauritian Rupee",
        "targetCurrency": "TMT",
        "targetName": "New Turkmenistan Manat",
        "exchangeRate": "0.103906",
        "inverseRate": "9.624068",
        "inverseDescription": "1 New Turkmenistan Manat = 9.624068 Mauritian Rupee"
      },
      {
        "title": "1 MUR = 0.230860 NOK",
        "link": "http://www.floatrates.com/mur/nok/",
        "description": "1 Mauritian Rupee = 0.230860 Norwegian Krone",
        "pubDate": null,
        "baseCurrency": "MUR",
        "baseName": "Mauritian Rupee",
        "targetCurrency": "NOK",
        "targetName": "Norwegian Krone",
        "exchangeRate": "0.230860",
        "inverseRate": "4.331639",
        "inverseDescription": "1 Norwegian Krone = 4.331639 Mauritian Rupee"
      },
      {
        "title": "1 MUR = 0.100723 PLN",
        "link": "http://www.floatrates.com/mur/pln/",
        "description": "1 Mauritian Rupee = 0.100723 Polish Zloty",
        "pubDate": null,
        "baseCurrency": "MUR",
        "baseName": "Mauritian Rupee",
        "targetCurrency": "PLN",
        "targetName": "Polish Zloty",
        "exchangeRate": "0.100723",
        "inverseRate": "9.928174",
        "inverseDescription": "1 Polish Zloty = 9.928174 Mauritian Rupee"
      },
      {
        "title": "1 MUR = 0.112466 RON",
        "link": "http://www.floatrates.com/mur/ron/",
        "description": "1 Mauritian Rupee = 0.112466 Romanian New Leu",
        "pubDate": null,
        "baseCurrency": "MUR",
        "baseName": "Mauritian Rupee",
        "targetCurrency": "RON",
        "targetName": "Romanian New Leu",
        "exchangeRate": "0.112466",
        "inverseRate": "8.891549",
        "inverseDescription": "1 Romanian New Leu = 8.891549 Mauritian Rupee"
      },
      {
        "title": "1 MUR = 0.262932 TJS",
        "link": "http://www.floatrates.com/mur/tjs/",
        "description": "1 Mauritian Rupee = 0.262932 Tajikistan Ruble",
        "pubDate": null,
        "baseCurrency": "MUR",
        "baseName": "Mauritian Rupee",
        "targetCurrency": "TJS",
        "targetName": "Tajikistan Ruble",
        "exchangeRate": "0.262932",
        "inverseRate": "3.803270",
        "inverseDescription": "1 Tajikistan Ruble = 3.803270 Mauritian Rupee"
      },
      {
        "title": "1 MUR = 0.121707 TRY",
        "link": "http://www.floatrates.com/mur/try/",
        "description": "1 Mauritian Rupee = 0.121707 Turkish Lira",
        "pubDate": null,
        "baseCurrency": "MUR",
        "baseName": "Mauritian Rupee",
        "targetCurrency": "TRY",
        "targetName": "Turkish Lira",
        "exchangeRate": "0.121707",
        "inverseRate": "8.216485",
        "inverseDescription": "1 Turkish Lira = 8.216485 Mauritian Rupee"
      },
      {
        "title": "1 MUR = 240.768201 UZS",
        "link": "http://www.floatrates.com/mur/uzs/",
        "description": "1 Mauritian Rupee = 240.768201 Uzbekistan Sum",
        "pubDate": null,
        "baseCurrency": "MUR",
        "baseName": "Mauritian Rupee",
        "targetCurrency": "UZS",
        "targetName": "Uzbekistan Sum",
        "exchangeRate": "240.768201",
        "inverseRate": "0.004153",
        "inverseDescription": "1 Uzbekistan Sum = 0.004153 Mauritian Rupee"
      },
      {
        "title": "1 MUR = 0.775535 UAH",
        "link": "http://www.floatrates.com/mur/uah/",
        "description": "1 Mauritian Rupee = 0.775535 Ukrainian Hryvnia",
        "pubDate": null,
        "baseCurrency": "MUR",
        "baseName": "Mauritian Rupee",
        "targetCurrency": "UAH",
        "targetName": "Ukrainian Hryvnia",
        "exchangeRate": "0.775535",
        "inverseRate": "1.289433",
        "inverseDescription": "1 Ukrainian Hryvnia = 1.289433 Mauritian Rupee"
      },
      {
        "title": "1 MUR = 0.610798 CZK",
        "link": "http://www.floatrates.com/mur/czk/",
        "description": "1 Mauritian Rupee = 0.610798 Czech Koruna",
        "pubDate": null,
        "baseCurrency": "MUR",
        "baseName": "Mauritian Rupee",
        "targetCurrency": "CZK",
        "targetName": "Czech Koruna",
        "exchangeRate": "0.610798",
        "inverseRate": "1.637202",
        "inverseDescription": "1 Czech Koruna = 1.637202 Mauritian Rupee"
      },
      {
        "title": "1 MUR = 0.250630 SEK",
        "link": "http://www.floatrates.com/mur/sek/",
        "description": "1 Mauritian Rupee = 0.250630 Swedish Krona",
        "pubDate": null,
        "baseCurrency": "MUR",
        "baseName": "Mauritian Rupee",
        "targetCurrency": "SEK",
        "targetName": "Swedish Krona",
        "exchangeRate": "0.250630",
        "inverseRate": "3.989948",
        "inverseDescription": "1 Swedish Krona = 3.989948 Mauritian Rupee"
      },
      {
        "title": "1 MUR = 0.358513 ZAR",
        "link": "http://www.floatrates.com/mur/zar/",
        "description": "1 Mauritian Rupee = 0.358513 South African Rand",
        "pubDate": null,
        "baseCurrency": "MUR",
        "baseName": "Mauritian Rupee",
        "targetCurrency": "ZAR",
        "targetName": "South African Rand",
        "exchangeRate": "0.358513",
        "inverseRate": "2.789298",
        "inverseDescription": "1 South African Rand = 2.789298 Mauritian Rupee"
      },
      {
        "title": "1 MUR = 1.835689 RUB",
        "link": "http://www.floatrates.com/mur/rub/",
        "description": "1 Mauritian Rupee = 1.835689 Russian Rouble",
        "pubDate": null,
        "baseCurrency": "MUR",
        "baseName": "Mauritian Rupee",
        "targetCurrency": "RUB",
        "targetName": "Russian Rouble",
        "exchangeRate": "1.835689",
        "inverseRate": "0.544754",
        "inverseDescription": "1 Russian Rouble = 0.544754 Mauritian Rupee"
      },
      {
        "title": "1 MUR = 0.104361 ILS",
        "link": "http://www.floatrates.com/mur/ils/",
        "description": "1 Mauritian Rupee = 0.104361 Israeli New Sheqel",
        "pubDate": null,
        "baseCurrency": "MUR",
        "baseName": "Mauritian Rupee",
        "targetCurrency": "ILS",
        "targetName": "Israeli New Sheqel",
        "exchangeRate": "0.104361",
        "inverseRate": "9.582139",
        "inverseDescription": "1 Israeli New Sheqel = 9.582139 Mauritian Rupee"
      },
      {
        "title": "1 MUR = 0.021093 JOD",
        "link": "http://www.floatrates.com/mur/jod/",
        "description": "1 Mauritian Rupee = 0.021093 Jordanian Dinar",
        "pubDate": null,
        "baseCurrency": "MUR",
        "baseName": "Mauritian Rupee",
        "targetCurrency": "JOD",
        "targetName": "Jordanian Dinar",
        "exchangeRate": "0.021093",
        "inverseRate": "47.408037",
        "inverseDescription": "1 Jordanian Dinar = 47.408037 Mauritian Rupee"
      },
      {
        "title": "1 MUR = 44.958542 LBP",
        "link": "http://www.floatrates.com/mur/lbp/",
        "description": "1 Mauritian Rupee = 44.958542 Lebanese Pound",
        "pubDate": null,
        "baseCurrency": "MUR",
        "baseName": "Mauritian Rupee",
        "targetCurrency": "LBP",
        "targetName": "Lebanese Pound",
        "exchangeRate": "44.958542",
        "inverseRate": "0.022243",
        "inverseDescription": "1 Lebanese Pound = 0.022243 Mauritian Rupee"
      },
      {
        "title": "1 MUR = 0.524166 EGP",
        "link": "http://www.floatrates.com/mur/egp/",
        "description": "1 Mauritian Rupee = 0.524166 Egyptian Pound",
        "pubDate": null,
        "baseCurrency": "MUR",
        "baseName": "Mauritian Rupee",
        "targetCurrency": "EGP",
        "targetName": "Egyptian Pound",
        "exchangeRate": "0.524166",
        "inverseRate": "1.907791",
        "inverseDescription": "1 Egyptian Pound = 1.907791 Mauritian Rupee"
      },
      {
        "title": "1 MUR = 2.932317 ISK",
        "link": "http://www.floatrates.com/mur/isk/",
        "description": "1 Mauritian Rupee = 2.932317 Icelandic Krona",
        "pubDate": null,
        "baseCurrency": "MUR",
        "baseName": "Mauritian Rupee",
        "targetCurrency": "ISK",
        "targetName": "Icelandic Krona",
        "exchangeRate": "2.932317",
        "inverseRate": "0.341027",
        "inverseDescription": "1 Icelandic Krona = 0.341027 Mauritian Rupee"
      },
      {
        "title": "1 MUR = 0.178994 HRK",
        "link": "http://www.floatrates.com/mur/hrk/",
        "description": "1 Mauritian Rupee = 0.178994 Croatian Kuna",
        "pubDate": null,
        "baseCurrency": "MUR",
        "baseName": "Mauritian Rupee",
        "targetCurrency": "HRK",
        "targetName": "Croatian Kuna",
        "exchangeRate": "0.178994",
        "inverseRate": "5.586779",
        "inverseDescription": "1 Croatian Kuna = 5.586779 Mauritian Rupee"
      },
      {
        "title": "1 MUR = 17.748217 CLP",
        "link": "http://www.floatrates.com/mur/clp/",
        "description": "1 Mauritian Rupee = 17.748217 Chilean Peso",
        "pubDate": null,
        "baseCurrency": "MUR",
        "baseName": "Mauritian Rupee",
        "targetCurrency": "CLP",
        "targetName": "Chilean Peso",
        "exchangeRate": "17.748217",
        "inverseRate": "0.056344",
        "inverseDescription": "1 Chilean Peso = 0.056344 Mauritian Rupee"
      },
      {
        "title": "1 MUR = 0.538157 MXN",
        "link": "http://www.floatrates.com/mur/mxn/",
        "description": "1 Mauritian Rupee = 0.538157 Mexican Peso",
        "pubDate": null,
        "baseCurrency": "MUR",
        "baseName": "Mauritian Rupee",
        "targetCurrency": "MXN",
        "targetName": "Mexican Peso",
        "exchangeRate": "0.538157",
        "inverseRate": "1.858193",
        "inverseDescription": "1 Mexican Peso = 1.858193 Mauritian Rupee"
      },
      {
        "title": "1 MUR = 1.544344 PHP",
        "link": "http://www.floatrates.com/mur/php/",
        "description": "1 Mauritian Rupee = 1.544344 Philippine Peso",
        "pubDate": null,
        "baseCurrency": "MUR",
        "baseName": "Mauritian Rupee",
        "targetCurrency": "PHP",
        "targetName": "Philippine Peso",
        "exchangeRate": "1.544344",
        "inverseRate": "0.647524",
        "inverseDescription": "1 Philippine Peso = 0.647524 Mauritian Rupee"
      },
      {
        "title": "1 MUR = 2.076572 AFN",
        "link": "http://www.floatrates.com/mur/afn/",
        "description": "1 Mauritian Rupee = 2.076572 Afghan afghani",
        "pubDate": null,
        "baseCurrency": "MUR",
        "baseName": "Mauritian Rupee",
        "targetCurrency": "AFN",
        "targetName": "Afghan afghani",
        "exchangeRate": "2.076572",
        "inverseRate": "0.481563",
        "inverseDescription": "1 Afghan afghani = 0.481563 Mauritian Rupee"
      },
      {
        "title": "1 MUR = 95.701949 MGA",
        "link": "http://www.floatrates.com/mur/mga/",
        "description": "1 Mauritian Rupee = 95.701949 Malagasy ariary",
        "pubDate": null,
        "baseCurrency": "MUR",
        "baseName": "Mauritian Rupee",
        "targetCurrency": "MGA",
        "targetName": "Malagasy ariary",
        "exchangeRate": "95.701949",
        "inverseRate": "0.010449",
        "inverseDescription": "1 Malagasy ariary = 0.010449 Mauritian Rupee"
      },
      {
        "title": "1 MUR = 0.029735 PAB",
        "link": "http://www.floatrates.com/mur/pab/",
        "description": "1 Mauritian Rupee = 0.029735 Panamanian Balboa",
        "pubDate": null,
        "baseCurrency": "MUR",
        "baseName": "Mauritian Rupee",
        "targetCurrency": "PAB",
        "targetName": "Panamanian Balboa",
        "exchangeRate": "0.029735",
        "inverseRate": "33.630832",
        "inverseDescription": "1 Panamanian Balboa = 33.630832 Mauritian Rupee"
      },
      {
        "title": "1 MUR = 0.815210 ETB",
        "link": "http://www.floatrates.com/mur/etb/",
        "description": "1 Mauritian Rupee = 0.815210 Ethiopian birr",
        "pubDate": null,
        "baseCurrency": "MUR",
        "baseName": "Mauritian Rupee",
        "targetCurrency": "ETB",
        "targetName": "Ethiopian birr",
        "exchangeRate": "0.815210",
        "inverseRate": "1.226678",
        "inverseDescription": "1 Ethiopian birr = 1.226678 Mauritian Rupee"
      },
      {
        "title": "1 MUR = 1,461.158207 VEF",
        "link": "http://www.floatrates.com/mur/vef/",
        "description": "1 Mauritian Rupee = 1,461.158207 Venezuelan Bolivar (till 20 August 2018)",
        "pubDate": null,
        "baseCurrency": "MUR",
        "baseName": "Mauritian Rupee",
        "targetCurrency": "VEF",
        "targetName": "Venezuelan Bolivar (till 20 August 2018)",
        "exchangeRate": "1,461.158207",
        "inverseRate": "0.000684",
        "inverseDescription": "1 Venezuelan Bolivar (till 20 August 2018) = 0.000684 Mauritian Rupee"
      },
      {
        "title": "1 MUR = 0.205980 BOB",
        "link": "http://www.floatrates.com/mur/bob/",
        "description": "1 Mauritian Rupee = 0.205980 Bolivian Boliviano",
        "pubDate": null,
        "baseCurrency": "MUR",
        "baseName": "Mauritian Rupee",
        "targetCurrency": "BOB",
        "targetName": "Bolivian Boliviano",
        "exchangeRate": "0.205980",
        "inverseRate": "4.854847",
        "inverseDescription": "1 Bolivian Boliviano = 4.854847 Mauritian Rupee"
      },
      {
        "title": "1 MUR = 16.854284 CRC",
        "link": "http://www.floatrates.com/mur/crc/",
        "description": "1 Mauritian Rupee = 16.854284 Costa Rican Col\u00f3n",
        "pubDate": null,
        "baseCurrency": "MUR",
        "baseName": "Mauritian Rupee",
        "targetCurrency": "CRC",
        "targetName": "Costa Rican Col\u00f3n",
        "exchangeRate": "16.854284",
        "inverseRate": "0.059332",
        "inverseDescription": "1 Costa Rican Col\u00f3n = 0.059332 Mauritian Rupee"
      },
      {
        "title": "1 MUR = 0.260286 SVC",
        "link": "http://www.floatrates.com/mur/svc/",
        "description": "1 Mauritian Rupee = 0.260286 Salvadoran colon",
        "pubDate": null,
        "baseCurrency": "MUR",
        "baseName": "Mauritian Rupee",
        "targetCurrency": "SVC",
        "targetName": "Salvadoran colon",
        "exchangeRate": "0.260286",
        "inverseRate": "3.841934",
        "inverseDescription": "1 Salvadoran colon = 3.841934 Mauritian Rupee"
      },
      {
        "title": "1 MUR = 1.420006 GMD",
        "link": "http://www.floatrates.com/mur/gmd/",
        "description": "1 Mauritian Rupee = 1.420006 Gambian dalasi",
        "pubDate": null,
        "baseCurrency": "MUR",
        "baseName": "Mauritian Rupee",
        "targetCurrency": "GMD",
        "targetName": "Gambian dalasi",
        "exchangeRate": "1.420006",
        "inverseRate": "0.704222",
        "inverseDescription": "1 Gambian dalasi = 0.704222 Mauritian Rupee"
      },
      {
        "title": "1 MUR = 1.477350 MKD",
        "link": "http://www.floatrates.com/mur/mkd/",
        "description": "1 Mauritian Rupee = 1.477350 Macedonian denar",
        "pubDate": null,
        "baseCurrency": "MUR",
        "baseName": "Mauritian Rupee",
        "targetCurrency": "MKD",
        "targetName": "Macedonian denar",
        "exchangeRate": "1.477350",
        "inverseRate": "0.676888",
        "inverseDescription": "1 Macedonian denar = 0.676888 Mauritian Rupee"
      },
      {
        "title": "1 MUR = 3.390795 DZD",
        "link": "http://www.floatrates.com/mur/dzd/",
        "description": "1 Mauritian Rupee = 3.390795 Algerian Dinar",
        "pubDate": null,
        "baseCurrency": "MUR",
        "baseName": "Mauritian Rupee",
        "targetCurrency": "DZD",
        "targetName": "Algerian Dinar",
        "exchangeRate": "3.390795",
        "inverseRate": "0.294916",
        "inverseDescription": "1 Algerian Dinar = 0.294916 Mauritian Rupee"
      },
      {
        "title": "1 MUR = 0.011180 BHD",
        "link": "http://www.floatrates.com/mur/bhd/",
        "description": "1 Mauritian Rupee = 0.011180 Bahrain Dinar",
        "pubDate": null,
        "baseCurrency": "MUR",
        "baseName": "Mauritian Rupee",
        "targetCurrency": "BHD",
        "targetName": "Bahrain Dinar",
        "exchangeRate": "0.011180",
        "inverseRate": "89.441790",
        "inverseDescription": "1 Bahrain Dinar = 89.441790 Mauritian Rupee"
      },
      {
        "title": "1 MUR = 35.475141 IQD",
        "link": "http://www.floatrates.com/mur/iqd/",
        "description": "1 Mauritian Rupee = 35.475141 Iraqi dinar",
        "pubDate": null,
        "baseCurrency": "MUR",
        "baseName": "Mauritian Rupee",
        "targetCurrency": "IQD",
        "targetName": "Iraqi dinar",
        "exchangeRate": "35.475141",
        "inverseRate": "0.028189",
        "inverseDescription": "1 Iraqi dinar = 0.028189 Mauritian Rupee"
      },
      {
        "title": "1 MUR = 0.008911 KWD",
        "link": "http://www.floatrates.com/mur/kwd/",
        "description": "1 Mauritian Rupee = 0.008911 Kuwaiti Dinar",
        "pubDate": null,
        "baseCurrency": "MUR",
        "baseName": "Mauritian Rupee",
        "targetCurrency": "KWD",
        "targetName": "Kuwaiti Dinar",
        "exchangeRate": "0.008911",
        "inverseRate": "112.225482",
        "inverseDescription": "1 Kuwaiti Dinar = 112.225482 Mauritian Rupee"
      },
      {
        "title": "1 MUR = 0.021353 LYD",
        "link": "http://www.floatrates.com/mur/lyd/",
        "description": "1 Mauritian Rupee = 0.021353 Libyan Dinar",
        "pubDate": null,
        "baseCurrency": "MUR",
        "baseName": "Mauritian Rupee",
        "targetCurrency": "LYD",
        "targetName": "Libyan Dinar",
        "exchangeRate": "0.021353",
        "inverseRate": "46.832530",
        "inverseDescription": "1 Libyan Dinar = 46.832530 Mauritian Rupee"
      },
      {
        "title": "1 MUR = 2.843406 RSD",
        "link": "http://www.floatrates.com/mur/rsd/",
        "description": "1 Mauritian Rupee = 2.843406 Serbian Dinar",
        "pubDate": null,
        "baseCurrency": "MUR",
        "baseName": "Mauritian Rupee",
        "targetCurrency": "RSD",
        "targetName": "Serbian Dinar",
        "exchangeRate": "2.843406",
        "inverseRate": "0.351691",
        "inverseDescription": "1 Serbian Dinar = 0.351691 Mauritian Rupee"
      },
      {
        "title": "1 MUR = 0.072118 TND",
        "link": "http://www.floatrates.com/mur/tnd/",
        "description": "1 Mauritian Rupee = 0.072118 Tunisian Dinar",
        "pubDate": null,
        "baseCurrency": "MUR",
        "baseName": "Mauritian Rupee",
        "targetCurrency": "TND",
        "targetName": "Tunisian Dinar",
        "exchangeRate": "0.072118",
        "inverseRate": "13.866234",
        "inverseDescription": "1 Tunisian Dinar = 13.866234 Mauritian Rupee"
      },
      {
        "title": "1 MUR = 0.272398 MAD",
        "link": "http://www.floatrates.com/mur/mad/",
        "description": "1 Mauritian Rupee = 0.272398 Moroccan Dirham",
        "pubDate": null,
        "baseCurrency": "MUR",
        "baseName": "Mauritian Rupee",
        "targetCurrency": "MAD",
        "targetName": "Moroccan Dirham",
        "exchangeRate": "0.272398",
        "inverseRate": "3.671093",
        "inverseDescription": "1 Moroccan Dirham = 3.671093 Mauritian Rupee"
      },
      {
        "title": "1 MUR = 0.606497 STN",
        "link": "http://www.floatrates.com/mur/stn/",
        "description": "1 Mauritian Rupee = 0.606497 S\u00e3o Tom\u00e9 and Pr\u00edncipe Dobra",
        "pubDate": null,
        "baseCurrency": "MUR",
        "baseName": "Mauritian Rupee",
        "targetCurrency": "STN",
        "targetName": "S\u00e3o Tom\u00e9 and Pr\u00edncipe Dobra",
        "exchangeRate": "0.606497",
        "inverseRate": "1.648814",
        "inverseDescription": "1 S\u00e3o Tom\u00e9 and Pr\u00edncipe Dobra = 1.648814 Mauritian Rupee"
      },
      {
        "title": "1 MUR = 0.029735 BSD",
        "link": "http://www.floatrates.com/mur/bsd/",
        "description": "1 Mauritian Rupee = 0.029735 Bahamian Dollar",
        "pubDate": null,
        "baseCurrency": "MUR",
        "baseName": "Mauritian Rupee",
        "targetCurrency": "BSD",
        "targetName": "Bahamian Dollar",
        "exchangeRate": "0.029735",
        "inverseRate": "33.630832",
        "inverseDescription": "1 Bahamian Dollar = 33.630832 Mauritian Rupee"
      },
      {
        "title": "1 MUR = 0.059466 BBD",
        "link": "http://www.floatrates.com/mur/bbd/",
        "description": "1 Mauritian Rupee = 0.059466 Barbadian Dollar",
        "pubDate": null,
        "baseCurrency": "MUR",
        "baseName": "Mauritian Rupee",
        "targetCurrency": "BBD",
        "targetName": "Barbadian Dollar",
        "exchangeRate": "0.059466",
        "inverseRate": "16.816338",
        "inverseDescription": "1 Barbadian Dollar = 16.816338 Mauritian Rupee"
      },
      {
        "title": "1 MUR = 0.059757 BZD",
        "link": "http://www.floatrates.com/mur/bzd/",
        "description": "1 Mauritian Rupee = 0.059757 Belize dollar",
        "pubDate": null,
        "baseCurrency": "MUR",
        "baseName": "Mauritian Rupee",
        "targetCurrency": "BZD",
        "targetName": "Belize dollar",
        "exchangeRate": "0.059757",
        "inverseRate": "16.734465",
        "inverseDescription": "1 Belize dollar = 16.734465 Mauritian Rupee"
      },
      {
        "title": "1 MUR = 0.039012 BND",
        "link": "http://www.floatrates.com/mur/bnd/",
        "description": "1 Mauritian Rupee = 0.039012 Brunei Dollar",
        "pubDate": null,
        "baseCurrency": "MUR",
        "baseName": "Mauritian Rupee",
        "targetCurrency": "BND",
        "targetName": "Brunei Dollar",
        "exchangeRate": "0.039012",
        "inverseRate": "25.633000",
        "inverseDescription": "1 Brunei Dollar = 25.633000 Mauritian Rupee"
      },
      {
        "title": "1 MUR = 0.060359 FJD",
        "link": "http://www.floatrates.com/mur/fjd/",
        "description": "1 Mauritian Rupee = 0.060359 Fiji Dollar",
        "pubDate": null,
        "baseCurrency": "MUR",
        "baseName": "Mauritian Rupee",
        "targetCurrency": "FJD",
        "targetName": "Fiji Dollar",
        "exchangeRate": "0.060359",
        "inverseRate": "16.567597",
        "inverseDescription": "1 Fiji Dollar = 16.567597 Mauritian Rupee"
      },
      {
        "title": "1 MUR = 6.143800 GYD",
        "link": "http://www.floatrates.com/mur/gyd/",
        "description": "1 Mauritian Rupee = 6.143800 Guyanese dollar",
        "pubDate": null,
        "baseCurrency": "MUR",
        "baseName": "Mauritian Rupee",
        "targetCurrency": "GYD",
        "targetName": "Guyanese dollar",
        "exchangeRate": "6.143800",
        "inverseRate": "0.162766",
        "inverseDescription": "1 Guyanese dollar = 0.162766 Mauritian Rupee"
      },
      {
        "title": "1 MUR = 3.701414 JMD",
        "link": "http://www.floatrates.com/mur/jmd/",
        "description": "1 Mauritian Rupee = 3.701414 Jamaican Dollar",
        "pubDate": null,
        "baseCurrency": "MUR",
        "baseName": "Mauritian Rupee",
        "targetCurrency": "JMD",
        "targetName": "Jamaican Dollar",
        "exchangeRate": "3.701414",
        "inverseRate": "0.270167",
        "inverseDescription": "1 Jamaican Dollar = 0.270167 Mauritian Rupee"
      },
      {
        "title": "1 MUR = 4.011094 LRD",
        "link": "http://www.floatrates.com/mur/lrd/",
        "description": "1 Mauritian Rupee = 4.011094 Liberian dollar",
        "pubDate": null,
        "baseCurrency": "MUR",
        "baseName": "Mauritian Rupee",
        "targetCurrency": "LRD",
        "targetName": "Liberian dollar",
        "exchangeRate": "4.011094",
        "inverseRate": "0.249309",
        "inverseDescription": "1 Liberian dollar = 0.249309 Mauritian Rupee"
      },
      {
        "title": "1 MUR = 0.357904 NAD",
        "link": "http://www.floatrates.com/mur/nad/",
        "description": "1 Mauritian Rupee = 0.357904 Namibian dollar",
        "pubDate": null,
        "baseCurrency": "MUR",
        "baseName": "Mauritian Rupee",
        "targetCurrency": "NAD",
        "targetName": "Namibian dollar",
        "exchangeRate": "0.357904",
        "inverseRate": "2.794044",
        "inverseDescription": "1 Namibian dollar = 2.794044 Mauritian Rupee"
      },
      {
        "title": "1 MUR = 0.222248 SRD",
        "link": "http://www.floatrates.com/mur/srd/",
        "description": "1 Mauritian Rupee = 0.222248 Surinamese dollar",
        "pubDate": null,
        "baseCurrency": "MUR",
        "baseName": "Mauritian Rupee",
        "targetCurrency": "SRD",
        "targetName": "Surinamese dollar",
        "exchangeRate": "0.222248",
        "inverseRate": "4.499473",
        "inverseDescription": "1 Surinamese dollar = 4.499473 Mauritian Rupee"
      },
      {
        "title": "1 MUR = 0.200563 TTD",
        "link": "http://www.floatrates.com/mur/ttd/",
        "description": "1 Mauritian Rupee = 0.200563 Trinidad Tobago Dollar",
        "pubDate": null,
        "baseCurrency": "MUR",
        "baseName": "Mauritian Rupee",
        "targetCurrency": "TTD",
        "targetName": "Trinidad Tobago Dollar",
        "exchangeRate": "0.200563",
        "inverseRate": "4.985976",
        "inverseDescription": "1 Trinidad Tobago Dollar = 4.985976 Mauritian Rupee"
      },
      {
        "title": "1 MUR = 0.080594 XCD",
        "link": "http://www.floatrates.com/mur/xcd/",
        "description": "1 Mauritian Rupee = 0.080594 East Caribbean Dollar",
        "pubDate": null,
        "baseCurrency": "MUR",
        "baseName": "Mauritian Rupee",
        "targetCurrency": "XCD",
        "targetName": "East Caribbean Dollar",
        "exchangeRate": "0.080594",
        "inverseRate": "12.407819",
        "inverseDescription": "1 East Caribbean Dollar = 12.407819 Mauritian Rupee"
      },
      {
        "title": "1 MUR = 0.230597 SBD",
        "link": "http://www.floatrates.com/mur/sbd/",
        "description": "1 Mauritian Rupee = 0.230597 Solomon Islands dollar",
        "pubDate": null,
        "baseCurrency": "MUR",
        "baseName": "Mauritian Rupee",
        "targetCurrency": "SBD",
        "targetName": "Solomon Islands dollar",
        "exchangeRate": "0.230597",
        "inverseRate": "4.336578",
        "inverseDescription": "1 Solomon Islands dollar = 4.336578 Mauritian Rupee"
      },
      {
        "title": "1 MUR = 2.663451 CVE",
        "link": "http://www.floatrates.com/mur/cve/",
        "description": "1 Mauritian Rupee = 2.663451 Cape Verde escudo",
        "pubDate": null,
        "baseCurrency": "MUR",
        "baseName": "Mauritian Rupee",
        "targetCurrency": "CVE",
        "targetName": "Cape Verde escudo",
        "exchangeRate": "2.663451",
        "inverseRate": "0.375453",
        "inverseDescription": "1 Cape Verde escudo = 0.375453 Mauritian Rupee"
      },
      {
        "title": "1 MUR = 0.053064 AWG",
        "link": "http://www.floatrates.com/mur/awg/",
        "description": "1 Mauritian Rupee = 0.053064 Aruban florin",
        "pubDate": null,
        "baseCurrency": "MUR",
        "baseName": "Mauritian Rupee",
        "targetCurrency": "AWG",
        "targetName": "Aruban florin",
        "exchangeRate": "0.053064",
        "inverseRate": "18.845145",
        "inverseDescription": "1 Aruban florin = 18.845145 Mauritian Rupee"
      },
      {
        "title": "1 MUR = 52.354888 BIF",
        "link": "http://www.floatrates.com/mur/bif/",
        "description": "1 Mauritian Rupee = 52.354888 Burundian franc",
        "pubDate": null,
        "baseCurrency": "MUR",
        "baseName": "Mauritian Rupee",
        "targetCurrency": "BIF",
        "targetName": "Burundian franc",
        "exchangeRate": "52.354888",
        "inverseRate": "0.019100",
        "inverseDescription": "1 Burundian franc = 0.019100 Mauritian Rupee"
      },
      {
        "title": "1 MUR = 15.836020 XOF",
        "link": "http://www.floatrates.com/mur/xof/",
        "description": "1 Mauritian Rupee = 15.836020 West African CFA Franc",
        "pubDate": null,
        "baseCurrency": "MUR",
        "baseName": "Mauritian Rupee",
        "targetCurrency": "XOF",
        "targetName": "West African CFA Franc",
        "exchangeRate": "15.836020",
        "inverseRate": "0.063147",
        "inverseDescription": "1 West African CFA Franc = 0.063147 Mauritian Rupee"
      },
      {
        "title": "1 MUR = 15.836020 XAF",
        "link": "http://www.floatrates.com/mur/xaf/",
        "description": "1 Mauritian Rupee = 15.836020 Central African CFA Franc",
        "pubDate": null,
        "baseCurrency": "MUR",
        "baseName": "Mauritian Rupee",
        "targetCurrency": "XAF",
        "targetName": "Central African CFA Franc",
        "exchangeRate": "15.836020",
        "inverseRate": "0.063147",
        "inverseDescription": "1 Central African CFA Franc = 0.063147 Mauritian Rupee"
      },
      {
        "title": "1 MUR = 2.866290 XPF",
        "link": "http://www.floatrates.com/mur/xpf/",
        "description": "1 Mauritian Rupee = 2.866290 CFP Franc",
        "pubDate": null,
        "baseCurrency": "MUR",
        "baseName": "Mauritian Rupee",
        "targetCurrency": "XPF",
        "targetName": "CFP Franc",
        "exchangeRate": "2.866290",
        "inverseRate": "0.348883",
        "inverseDescription": "1 CFP Franc = 0.348883 Mauritian Rupee"
      },
      {
        "title": "1 MUR = 5.260382 DJF",
        "link": "http://www.floatrates.com/mur/djf/",
        "description": "1 Mauritian Rupee = 5.260382 Djiboutian franc",
        "pubDate": null,
        "baseCurrency": "MUR",
        "baseName": "Mauritian Rupee",
        "targetCurrency": "DJF",
        "targetName": "Djiboutian franc",
        "exchangeRate": "5.260382",
        "inverseRate": "0.190100",
        "inverseDescription": "1 Djiboutian franc = 0.190100 Mauritian Rupee"
      },
      {
        "title": "1 MUR = 268.475867 GNF",
        "link": "http://www.floatrates.com/mur/gnf/",
        "description": "1 Mauritian Rupee = 268.475867 Guinean franc",
        "pubDate": null,
        "baseCurrency": "MUR",
        "baseName": "Mauritian Rupee",
        "targetCurrency": "GNF",
        "targetName": "Guinean franc",
        "exchangeRate": "268.475867",
        "inverseRate": "0.003725",
        "inverseDescription": "1 Guinean franc = 0.003725 Mauritian Rupee"
      },
      {
        "title": "1 MUR = 11.843130 KMF",
        "link": "http://www.floatrates.com/mur/kmf/",
        "description": "1 Mauritian Rupee = 11.843130 \tComoro franc",
        "pubDate": null,
        "baseCurrency": "MUR",
        "baseName": "Mauritian Rupee",
        "targetCurrency": "KMF",
        "targetName": "Comoro franc",
        "exchangeRate": "11.843130",
        "inverseRate": "0.084437",
        "inverseDescription": "1 \tComoro franc = 0.084437 Mauritian Rupee"
      },
      {
        "title": "1 MUR = 47.782843 CDF",
        "link": "http://www.floatrates.com/mur/cdf/",
        "description": "1 Mauritian Rupee = 47.782843 Congolese franc",
        "pubDate": null,
        "baseCurrency": "MUR",
        "baseName": "Mauritian Rupee",
        "targetCurrency": "CDF",
        "targetName": "Congolese franc",
        "exchangeRate": "47.782843",
        "inverseRate": "0.020928",
        "inverseDescription": "1 Congolese franc = 0.020928 Mauritian Rupee"
      },
      {
        "title": "1 MUR = 25.762142 RWF",
        "link": "http://www.floatrates.com/mur/rwf/",
        "description": "1 Mauritian Rupee = 25.762142 Rwandan franc",
        "pubDate": null,
        "baseCurrency": "MUR",
        "baseName": "Mauritian Rupee",
        "targetCurrency": "RWF",
        "targetName": "Rwandan franc",
        "exchangeRate": "25.762142",
        "inverseRate": "0.038817",
        "inverseDescription": "1 Rwandan franc = 0.038817 Mauritian Rupee"
      },
      {
        "title": "1 MUR = 0.020945 GIP",
        "link": "http://www.floatrates.com/mur/gip/",
        "description": "1 Mauritian Rupee = 0.020945 Gibraltar pound",
        "pubDate": null,
        "baseCurrency": "MUR",
        "baseName": "Mauritian Rupee",
        "targetCurrency": "GIP",
        "targetName": "Gibraltar pound",
        "exchangeRate": "0.020945",
        "inverseRate": "47.745074",
        "inverseDescription": "1 Gibraltar pound = 47.745074 Mauritian Rupee"
      },
      {
        "title": "1 MUR = 3.981116 SSP",
        "link": "http://www.floatrates.com/mur/ssp/",
        "description": "1 Mauritian Rupee = 3.981116 South Sudanese pound",
        "pubDate": null,
        "baseCurrency": "MUR",
        "baseName": "Mauritian Rupee",
        "targetCurrency": "SSP",
        "targetName": "South Sudanese pound",
        "exchangeRate": "3.981116",
        "inverseRate": "0.251186",
        "inverseDescription": "1 South Sudanese pound = 0.251186 Mauritian Rupee"
      },
      {
        "title": "1 MUR = 0.540120 SDG",
        "link": "http://www.floatrates.com/mur/sdg/",
        "description": "1 Mauritian Rupee = 0.540120 Sudanese pound",
        "pubDate": null,
        "baseCurrency": "MUR",
        "baseName": "Mauritian Rupee",
        "targetCurrency": "SDG",
        "targetName": "Sudanese pound",
        "exchangeRate": "0.540120",
        "inverseRate": "1.851439",
        "inverseDescription": "1 Sudanese pound = 1.851439 Mauritian Rupee"
      },
      {
        "title": "1 MUR = 15.254311 SYP",
        "link": "http://www.floatrates.com/mur/syp/",
        "description": "1 Mauritian Rupee = 15.254311 Syrian pound",
        "pubDate": null,
        "baseCurrency": "MUR",
        "baseName": "Mauritian Rupee",
        "targetCurrency": "SYP",
        "targetName": "Syrian pound",
        "exchangeRate": "15.254311",
        "inverseRate": "0.065555",
        "inverseDescription": "1 Syrian pound = 0.065555 Mauritian Rupee"
      },
      {
        "title": "1 MUR = 0.131709 GHS",
        "link": "http://www.floatrates.com/mur/ghs/",
        "description": "1 Mauritian Rupee = 0.131709 Ghanaian Cedi",
        "pubDate": null,
        "baseCurrency": "MUR",
        "baseName": "Mauritian Rupee",
        "targetCurrency": "GHS",
        "targetName": "Ghanaian Cedi",
        "exchangeRate": "0.131709",
        "inverseRate": "7.592489",
        "inverseDescription": "1 Ghanaian Cedi = 7.592489 Mauritian Rupee"
      },
      {
        "title": "1 MUR = 1.928706 HTG",
        "link": "http://www.floatrates.com/mur/htg/",
        "description": "1 Mauritian Rupee = 1.928706 Haitian gourde",
        "pubDate": null,
        "baseCurrency": "MUR",
        "baseName": "Mauritian Rupee",
        "targetCurrency": "HTG",
        "targetName": "Haitian gourde",
        "exchangeRate": "1.928706",
        "inverseRate": "0.518482",
        "inverseDescription": "1 Haitian gourde = 0.518482 Mauritian Rupee"
      },
      {
        "title": "1 MUR = 164.505248 PYG",
        "link": "http://www.floatrates.com/mur/pyg/",
        "description": "1 Mauritian Rupee = 164.505248 Paraguayan Guaran\u00ed",
        "pubDate": null,
        "baseCurrency": "MUR",
        "baseName": "Mauritian Rupee",
        "targetCurrency": "PYG",
        "targetName": "Paraguayan Guaran\u00ed",
        "exchangeRate": "164.505248",
        "inverseRate": "0.006079",
        "inverseDescription": "1 Paraguayan Guaran\u00ed = 0.006079 Mauritian Rupee"
      },
      {
        "title": "1 MUR = 0.053067 ANG",
        "link": "http://www.floatrates.com/mur/ang/",
        "description": "1 Mauritian Rupee = 0.053067 Neth. Antillean Guilder",
        "pubDate": null,
        "baseCurrency": "MUR",
        "baseName": "Mauritian Rupee",
        "targetCurrency": "ANG",
        "targetName": "Neth. Antillean Guilder",
        "exchangeRate": "0.053067",
        "inverseRate": "18.844152",
        "inverseDescription": "1 Neth. Antillean Guilder = 18.844152 Mauritian Rupee"
      },
      {
        "title": "1 MUR = 246.157579 LAK",
        "link": "http://www.floatrates.com/mur/lak/",
        "description": "1 Mauritian Rupee = 246.157579 Lao kip",
        "pubDate": null,
        "baseCurrency": "MUR",
        "baseName": "Mauritian Rupee",
        "targetCurrency": "LAK",
        "targetName": "Lao kip",
        "exchangeRate": "246.157579",
        "inverseRate": "0.004062",
        "inverseDescription": "1 Lao kip = 0.004062 Mauritian Rupee"
      },
      {
        "title": "1 MUR = 21.572413 MWK",
        "link": "http://www.floatrates.com/mur/mwk/",
        "description": "1 Mauritian Rupee = 21.572413 Malawian kwacha",
        "pubDate": null,
        "baseCurrency": "MUR",
        "baseName": "Mauritian Rupee",
        "targetCurrency": "MWK",
        "targetName": "Malawian kwacha",
        "exchangeRate": "21.572413",
        "inverseRate": "0.046356",
        "inverseDescription": "1 Malawian kwacha = 0.046356 Mauritian Rupee"
      },
      {
        "title": "1 MUR = 0.281697 ZMW",
        "link": "http://www.floatrates.com/mur/zmw/",
        "description": "1 Mauritian Rupee = 0.281697 Zambian kwacha",
        "pubDate": null,
        "baseCurrency": "MUR",
        "baseName": "Mauritian Rupee",
        "targetCurrency": "ZMW",
        "targetName": "Zambian kwacha",
        "exchangeRate": "0.281697",
        "inverseRate": "3.549916",
        "inverseDescription": "1 Zambian kwacha = 3.549916 Mauritian Rupee"
      },
      {
        "title": "1 MUR = 6.453747 AOA",
        "link": "http://www.floatrates.com/mur/aoa/",
        "description": "1 Mauritian Rupee = 6.453747 Angolan kwanza",
        "pubDate": null,
        "baseCurrency": "MUR",
        "baseName": "Mauritian Rupee",
        "targetCurrency": "AOA",
        "targetName": "Angolan kwanza",
        "exchangeRate": "6.453747",
        "inverseRate": "0.154949",
        "inverseDescription": "1 Angolan kwanza = 0.154949 Mauritian Rupee"
      },
      {
        "title": "1 MUR = 39.435351 MMK",
        "link": "http://www.floatrates.com/mur/mmk/",
        "description": "1 Mauritian Rupee = 39.435351 Myanma Kyat",
        "pubDate": null,
        "baseCurrency": "MUR",
        "baseName": "Mauritian Rupee",
        "targetCurrency": "MMK",
        "targetName": "Myanma Kyat",
        "exchangeRate": "39.435351",
        "inverseRate": "0.025358",
        "inverseDescription": "1 Myanma Kyat = 0.025358 Mauritian Rupee"
      },
      {
        "title": "1 MUR = 0.071368 GEL",
        "link": "http://www.floatrates.com/mur/gel/",
        "description": "1 Mauritian Rupee = 0.071368 Georgian lari",
        "pubDate": null,
        "baseCurrency": "MUR",
        "baseName": "Mauritian Rupee",
        "targetCurrency": "GEL",
        "targetName": "Georgian lari",
        "exchangeRate": "0.071368",
        "inverseRate": "14.011936",
        "inverseDescription": "1 Georgian lari = 14.011936 Mauritian Rupee"
      },
      {
        "title": "1 MUR = 3.109087 ALL",
        "link": "http://www.floatrates.com/mur/all/",
        "description": "1 Mauritian Rupee = 3.109087 Albanian lek",
        "pubDate": null,
        "baseCurrency": "MUR",
        "baseName": "Mauritian Rupee",
        "targetCurrency": "ALL",
        "targetName": "Albanian lek",
        "exchangeRate": "3.109087",
        "inverseRate": "0.321638",
        "inverseDescription": "1 Albanian lek = 0.321638 Mauritian Rupee"
      },
      {
        "title": "1 MUR = 0.704538 HNL",
        "link": "http://www.floatrates.com/mur/hnl/",
        "description": "1 Mauritian Rupee = 0.704538 Honduran Lempira",
        "pubDate": null,
        "baseCurrency": "MUR",
        "baseName": "Mauritian Rupee",
        "targetCurrency": "HNL",
        "targetName": "Honduran Lempira",
        "exchangeRate": "0.704538",
        "inverseRate": "1.419370",
        "inverseDescription": "1 Honduran Lempira = 1.419370 Mauritian Rupee"
      },
      {
        "title": "1 MUR = 232.513741 SLL",
        "link": "http://www.floatrates.com/mur/sll/",
        "description": "1 Mauritian Rupee = 232.513741 Sierra Leonean leone",
        "pubDate": null,
        "baseCurrency": "MUR",
        "baseName": "Mauritian Rupee",
        "targetCurrency": "SLL",
        "targetName": "Sierra Leonean leone",
        "exchangeRate": "232.513741",
        "inverseRate": "0.004301",
        "inverseDescription": "1 Sierra Leonean leone = 0.004301 Mauritian Rupee"
      },
      {
        "title": "1 MUR = 0.357904 SZL",
        "link": "http://www.floatrates.com/mur/szl/",
        "description": "1 Mauritian Rupee = 0.357904 Swazi lilangeni",
        "pubDate": null,
        "baseCurrency": "MUR",
        "baseName": "Mauritian Rupee",
        "targetCurrency": "SZL",
        "targetName": "Swazi lilangeni",
        "exchangeRate": "0.357904",
        "inverseRate": "2.794044",
        "inverseDescription": "1 Swazi lilangeni = 2.794044 Mauritian Rupee"
      },
      {
        "title": "1 MUR = 0.358031 LSL",
        "link": "http://www.floatrates.com/mur/lsl/",
        "description": "1 Mauritian Rupee = 0.358031 Lesotho loti",
        "pubDate": null,
        "baseCurrency": "MUR",
        "baseName": "Mauritian Rupee",
        "targetCurrency": "LSL",
        "targetName": "Lesotho loti",
        "exchangeRate": "0.358031",
        "inverseRate": "2.793051",
        "inverseDescription": "1 Lesotho loti = 2.793051 Mauritian Rupee"
      },
      {
        "title": "1 MUR = 1.837198 MZN",
        "link": "http://www.floatrates.com/mur/mzn/",
        "description": "1 Mauritian Rupee = 1.837198 Mozambican metical",
        "pubDate": null,
        "baseCurrency": "MUR",
        "baseName": "Mauritian Rupee",
        "targetCurrency": "MZN",
        "targetName": "Mozambican metical",
        "exchangeRate": "1.837198",
        "inverseRate": "0.544307",
        "inverseDescription": "1 Mozambican metical = 0.544307 Mauritian Rupee"
      },
      {
        "title": "1 MUR = 9.062782 NGN",
        "link": "http://www.floatrates.com/mur/ngn/",
        "description": "1 Mauritian Rupee = 9.062782 Nigerian Naira",
        "pubDate": null,
        "baseCurrency": "MUR",
        "baseName": "Mauritian Rupee",
        "targetCurrency": "NGN",
        "targetName": "Nigerian Naira",
        "exchangeRate": "9.062782",
        "inverseRate": "0.110341",
        "inverseDescription": "1 Nigerian Naira = 0.110341 Mauritian Rupee"
      },
      {
        "title": "1 MUR = 0.448057 ERN",
        "link": "http://www.floatrates.com/mur/ern/",
        "description": "1 Mauritian Rupee = 0.448057 Eritrean nakfa",
        "pubDate": null,
        "baseCurrency": "MUR",
        "baseName": "Mauritian Rupee",
        "targetCurrency": "ERN",
        "targetName": "Eritrean nakfa",
        "exchangeRate": "0.448057",
        "inverseRate": "2.231858",
        "inverseDescription": "1 Eritrean nakfa = 2.231858 Mauritian Rupee"
      },
      {
        "title": "1 MUR = 1.049827 MRU",
        "link": "http://www.floatrates.com/mur/mru/",
        "description": "1 Mauritian Rupee = 1.049827 Mauritanian ouguiya",
        "pubDate": null,
        "baseCurrency": "MUR",
        "baseName": "Mauritian Rupee",
        "targetCurrency": "MRU",
        "targetName": "Mauritanian ouguiya",
        "exchangeRate": "1.049827",
        "inverseRate": "0.952538",
        "inverseDescription": "1 Mauritanian ouguiya = 0.952538 Mauritian Rupee"
      },
      {
        "title": "1 MUR = 0.064500 TOP",
        "link": "http://www.floatrates.com/mur/top/",
        "description": "1 Mauritian Rupee = 0.064500 Tongan pa\u02bbanga",
        "pubDate": null,
        "baseCurrency": "MUR",
        "baseName": "Mauritian Rupee",
        "targetCurrency": "TOP",
        "targetName": "Tongan pa\u02bbanga",
        "exchangeRate": "0.064500",
        "inverseRate": "15.503814",
        "inverseDescription": "1 Tongan pa\u02bbanga = 15.503814 Mauritian Rupee"
      },
      {
        "title": "1 MUR = 0.240455 MOP",
        "link": "http://www.floatrates.com/mur/mop/",
        "description": "1 Mauritian Rupee = 0.240455 Macanese pataca",
        "pubDate": null,
        "baseCurrency": "MUR",
        "baseName": "Mauritian Rupee",
        "targetCurrency": "MOP",
        "targetName": "Macanese pataca",
        "exchangeRate": "0.240455",
        "inverseRate": "4.158785",
        "inverseDescription": "1 Macanese pataca = 4.158785 Mauritian Rupee"
      },
      {
        "title": "1 MUR = 0.599116 ARS",
        "link": "http://www.floatrates.com/mur/ars/",
        "description": "1 Mauritian Rupee = 0.599116 Argentine Peso",
        "pubDate": null,
        "baseCurrency": "MUR",
        "baseName": "Mauritian Rupee",
        "targetCurrency": "ARS",
        "targetName": "Argentine Peso",
        "exchangeRate": "0.599116",
        "inverseRate": "1.669127",
        "inverseDescription": "1 Argentine Peso = 1.669127 Mauritian Rupee"
      },
      {
        "title": "1 MUR = 1.471367 DOP",
        "link": "http://www.floatrates.com/mur/dop/",
        "description": "1 Mauritian Rupee = 1.471367 Dominican Peso",
        "pubDate": null,
        "baseCurrency": "MUR",
        "baseName": "Mauritian Rupee",
        "targetCurrency": "DOP",
        "targetName": "Dominican Peso",
        "exchangeRate": "1.471367",
        "inverseRate": "0.679640",
        "inverseDescription": "1 Dominican Peso = 0.679640 Mauritian Rupee"
      },
      {
        "title": "1 MUR = 80.660732 COP",
        "link": "http://www.floatrates.com/mur/cop/",
        "description": "1 Mauritian Rupee = 80.660732 Colombian Peso",
        "pubDate": null,
        "baseCurrency": "MUR",
        "baseName": "Mauritian Rupee",
        "targetCurrency": "COP",
        "targetName": "Colombian Peso",
        "exchangeRate": "80.660732",
        "inverseRate": "0.012398",
        "inverseDescription": "1 Colombian Peso = 0.012398 Mauritian Rupee"
      },
      {
        "title": "1 MUR = 0.029735 CUP",
        "link": "http://www.floatrates.com/mur/cup/",
        "description": "1 Mauritian Rupee = 0.029735 Cuban peso",
        "pubDate": null,
        "baseCurrency": "MUR",
        "baseName": "Mauritian Rupee",
        "targetCurrency": "CUP",
        "targetName": "Cuban peso",
        "exchangeRate": "0.029735",
        "inverseRate": "33.630832",
        "inverseDescription": "1 Cuban peso = 33.630832 Mauritian Rupee"
      },
      {
        "title": "1 MUR = 0.841221 UYU",
        "link": "http://www.floatrates.com/mur/uyu/",
        "description": "1 Mauritian Rupee = 0.841221 Uruguayan Peso",
        "pubDate": null,
        "baseCurrency": "MUR",
        "baseName": "Mauritian Rupee",
        "targetCurrency": "UYU",
        "targetName": "Uruguayan Peso",
        "exchangeRate": "0.841221",
        "inverseRate": "1.188748",
        "inverseDescription": "1 Uruguayan Peso = 1.188748 Mauritian Rupee"
      },
      {
        "title": "1 MUR = 0.286153 BWP",
        "link": "http://www.floatrates.com/mur/bwp/",
        "description": "1 Mauritian Rupee = 0.286153 Botswana Pula",
        "pubDate": null,
        "baseCurrency": "MUR",
        "baseName": "Mauritian Rupee",
        "targetCurrency": "BWP",
        "targetName": "Botswana Pula",
        "exchangeRate": "0.286153",
        "inverseRate": "3.494635",
        "inverseDescription": "1 Botswana Pula = 3.494635 Mauritian Rupee"
      },
      {
        "title": "1 MUR = 0.220496 GTQ",
        "link": "http://www.floatrates.com/mur/gtq/",
        "description": "1 Mauritian Rupee = 0.220496 Guatemalan Quetzal",
        "pubDate": null,
        "baseCurrency": "MUR",
        "baseName": "Mauritian Rupee",
        "targetCurrency": "GTQ",
        "targetName": "Guatemalan Quetzal",
        "exchangeRate": "0.220496",
        "inverseRate": "4.535231",
        "inverseDescription": "1 Guatemalan Quetzal = 4.535231 Mauritian Rupee"
      },
      {
        "title": "1 MUR = 1,245.865338 IRR",
        "link": "http://www.floatrates.com/mur/irr/",
        "description": "1 Mauritian Rupee = 1,245.865338 Iranian rial",
        "pubDate": null,
        "baseCurrency": "MUR",
        "baseName": "Mauritian Rupee",
        "targetCurrency": "IRR",
        "targetName": "Iranian rial",
        "exchangeRate": "1,245.865338",
        "inverseRate": "0.000803",
        "inverseDescription": "1 Iranian rial = 0.000803 Mauritian Rupee"
      },
      {
        "title": "1 MUR = 7.433984 YER",
        "link": "http://www.floatrates.com/mur/yer/",
        "description": "1 Mauritian Rupee = 7.433984 Yemeni rial",
        "pubDate": null,
        "baseCurrency": "MUR",
        "baseName": "Mauritian Rupee",
        "targetCurrency": "YER",
        "targetName": "Yemeni rial",
        "exchangeRate": "7.433984",
        "inverseRate": "0.134517",
        "inverseDescription": "1 Yemeni rial = 0.134517 Mauritian Rupee"
      },
      {
        "title": "1 MUR = 0.108264 QAR",
        "link": "http://www.floatrates.com/mur/qar/",
        "description": "1 Mauritian Rupee = 0.108264 Qatari Rial",
        "pubDate": null,
        "baseCurrency": "MUR",
        "baseName": "Mauritian Rupee",
        "targetCurrency": "QAR",
        "targetName": "Qatari Rial",
        "exchangeRate": "0.108264",
        "inverseRate": "9.236639",
        "inverseDescription": "1 Qatari Rial = 9.236639 Mauritian Rupee"
      },
      {
        "title": "1 MUR = 0.011431 OMR",
        "link": "http://www.floatrates.com/mur/omr/",
        "description": "1 Mauritian Rupee = 0.011431 Omani Rial",
        "pubDate": null,
        "baseCurrency": "MUR",
        "baseName": "Mauritian Rupee",
        "targetCurrency": "OMR",
        "targetName": "Omani Rial",
        "exchangeRate": "0.011431",
        "inverseRate": "87.482007",
        "inverseDescription": "1 Omani Rial = 87.482007 Mauritian Rupee"
      },
      {
        "title": "1 MUR = 0.111500 SAR",
        "link": "http://www.floatrates.com/mur/sar/",
        "description": "1 Mauritian Rupee = 0.111500 Saudi Riyal",
        "pubDate": null,
        "baseCurrency": "MUR",
        "baseName": "Mauritian Rupee",
        "targetCurrency": "SAR",
        "targetName": "Saudi Riyal",
        "exchangeRate": "0.111500",
        "inverseRate": "8.968589",
        "inverseDescription": "1 Saudi Riyal = 8.968589 Mauritian Rupee"
      },
      {
        "title": "1 MUR = 119.712782 KHR",
        "link": "http://www.floatrates.com/mur/khr/",
        "description": "1 Mauritian Rupee = 119.712782 Cambodian riel",
        "pubDate": null,
        "baseCurrency": "MUR",
        "baseName": "Mauritian Rupee",
        "targetCurrency": "KHR",
        "targetName": "Cambodian riel",
        "exchangeRate": "119.712782",
        "inverseRate": "0.008353",
        "inverseDescription": "1 Cambodian riel = 0.008353 Mauritian Rupee"
      },
      {
        "title": "1 MUR = 4.629669 LKR",
        "link": "http://www.floatrates.com/mur/lkr/",
        "description": "1 Mauritian Rupee = 4.629669 Sri Lanka Rupee",
        "pubDate": null,
        "baseCurrency": "MUR",
        "baseName": "Mauritian Rupee",
        "targetCurrency": "LKR",
        "targetName": "Sri Lanka Rupee",
        "exchangeRate": "4.629669",
        "inverseRate": "0.215998",
        "inverseDescription": "1 Sri Lanka Rupee = 0.215998 Mauritian Rupee"
      },
      {
        "title": "1 MUR = 0.459719 MVR",
        "link": "http://www.floatrates.com/mur/mvr/",
        "description": "1 Mauritian Rupee = 0.459719 Maldivian rufiyaa",
        "pubDate": null,
        "baseCurrency": "MUR",
        "baseName": "Mauritian Rupee",
        "targetCurrency": "MVR",
        "targetName": "Maldivian rufiyaa",
        "exchangeRate": "0.459719",
        "inverseRate": "2.175242",
        "inverseDescription": "1 Maldivian rufiyaa = 2.175242 Mauritian Rupee"
      },
      {
        "title": "1 MUR = 1.000000 MUR",
        "link": "http://www.floatrates.com/mur/mur/",
        "description": "1 Mauritian Rupee = 1.000000 Mauritian Rupee",
        "pubDate": null,
        "baseCurrency": "MUR",
        "baseName": "Mauritian Rupee",
        "targetCurrency": "MUR",
        "targetName": "Mauritian Rupee",
        "exchangeRate": "1.000000",
        "inverseRate": "1.000000",
        "inverseDescription": "1 Mauritian Rupee = 1.000000 Mauritian Rupee"
      },
      {
        "title": "1 MUR = 3.104335 NPR",
        "link": "http://www.floatrates.com/mur/npr/",
        "description": "1 Mauritian Rupee = 3.104335 Nepalese Rupee",
        "pubDate": null,
        "baseCurrency": "MUR",
        "baseName": "Mauritian Rupee",
        "targetCurrency": "NPR",
        "targetName": "Nepalese Rupee",
        "exchangeRate": "3.104335",
        "inverseRate": "0.322130",
        "inverseDescription": "1 Nepalese Rupee = 0.322130 Mauritian Rupee"
      },
      {
        "title": "1 MUR = 3.437353 PKR",
        "link": "http://www.floatrates.com/mur/pkr/",
        "description": "1 Mauritian Rupee = 3.437353 Pakistani Rupee",
        "pubDate": null,
        "baseCurrency": "MUR",
        "baseName": "Mauritian Rupee",
        "targetCurrency": "PKR",
        "targetName": "Pakistani Rupee",
        "exchangeRate": "3.437353",
        "inverseRate": "0.290922",
        "inverseDescription": "1 Pakistani Rupee = 0.290922 Mauritian Rupee"
      },
      {
        "title": "1 MUR = 0.399994 SCR",
        "link": "http://www.floatrates.com/mur/scr/",
        "description": "1 Mauritian Rupee = 0.399994 Seychelles rupee",
        "pubDate": null,
        "baseCurrency": "MUR",
        "baseName": "Mauritian Rupee",
        "targetCurrency": "SCR",
        "targetName": "Seychelles rupee",
        "exchangeRate": "0.399994",
        "inverseRate": "2.500038",
        "inverseDescription": "1 Seychelles rupee = 2.500038 Mauritian Rupee"
      },
      {
        "title": "1 MUR = 0.095907 PEN",
        "link": "http://www.floatrates.com/mur/pen/",
        "description": "1 Mauritian Rupee = 0.095907 Peruvian Nuevo Sol",
        "pubDate": null,
        "baseCurrency": "MUR",
        "baseName": "Mauritian Rupee",
        "targetCurrency": "PEN",
        "targetName": "Peruvian Nuevo Sol",
        "exchangeRate": "0.095907",
        "inverseRate": "10.426766",
        "inverseDescription": "1 Peruvian Nuevo Sol = 10.426766 Mauritian Rupee"
      },
      {
        "title": "1 MUR = 3.002727 KES",
        "link": "http://www.floatrates.com/mur/kes/",
        "description": "1 Mauritian Rupee = 3.002727 Kenyan shilling",
        "pubDate": null,
        "baseCurrency": "MUR",
        "baseName": "Mauritian Rupee",
        "targetCurrency": "KES",
        "targetName": "Kenyan shilling",
        "exchangeRate": "3.002727",
        "inverseRate": "0.333031",
        "inverseDescription": "1 Kenyan shilling = 0.333031 Mauritian Rupee"
      },
      {
        "title": "1 MUR = 17.198232 SOS",
        "link": "http://www.floatrates.com/mur/sos/",
        "description": "1 Mauritian Rupee = 17.198232 Somali shilling",
        "pubDate": null,
        "baseCurrency": "MUR",
        "baseName": "Mauritian Rupee",
        "targetCurrency": "SOS",
        "targetName": "Somali shilling",
        "exchangeRate": "17.198232",
        "inverseRate": "0.058146",
        "inverseDescription": "1 Somali shilling = 0.058146 Mauritian Rupee"
      },
      {
        "title": "1 MUR = 67.208578 TZS",
        "link": "http://www.floatrates.com/mur/tzs/",
        "description": "1 Mauritian Rupee = 67.208578 Tanzanian shilling",
        "pubDate": null,
        "baseCurrency": "MUR",
        "baseName": "Mauritian Rupee",
        "targetCurrency": "TZS",
        "targetName": "Tanzanian shilling",
        "exchangeRate": "67.208578",
        "inverseRate": "0.014879",
        "inverseDescription": "1 Tanzanian shilling = 0.014879 Mauritian Rupee"
      },
      {
        "title": "1 MUR = 110.031093 UGX",
        "link": "http://www.floatrates.com/mur/ugx/",
        "description": "1 Mauritian Rupee = 110.031093 Ugandan shilling",
        "pubDate": null,
        "baseCurrency": "MUR",
        "baseName": "Mauritian Rupee",
        "targetCurrency": "UGX",
        "targetName": "Ugandan shilling",
        "exchangeRate": "110.031093",
        "inverseRate": "0.009088",
        "inverseDescription": "1 Ugandan shilling = 0.009088 Mauritian Rupee"
      },
      {
        "title": "1 MUR = 2.466089 BDT",
        "link": "http://www.floatrates.com/mur/bdt/",
        "description": "1 Mauritian Rupee = 2.466089 Bangladeshi taka",
        "pubDate": null,
        "baseCurrency": "MUR",
        "baseName": "Mauritian Rupee",
        "targetCurrency": "BDT",
        "targetName": "Bangladeshi taka",
        "exchangeRate": "2.466089",
        "inverseRate": "0.405500",
        "inverseDescription": "1 Bangladeshi taka = 0.405500 Mauritian Rupee"
      },
      {
        "title": "1 MUR = 0.075550 WST",
        "link": "http://www.floatrates.com/mur/wst/",
        "description": "1 Mauritian Rupee = 0.075550 Samoan tala",
        "pubDate": null,
        "baseCurrency": "MUR",
        "baseName": "Mauritian Rupee",
        "targetCurrency": "WST",
        "targetName": "Samoan tala",
        "exchangeRate": "0.075550",
        "inverseRate": "13.236199",
        "inverseDescription": "1 Samoan tala = 13.236199 Mauritian Rupee"
      },
      {
        "title": "1 MUR = 71.150848 MNT",
        "link": "http://www.floatrates.com/mur/mnt/",
        "description": "1 Mauritian Rupee = 71.150848 Mongolian togrog",
        "pubDate": null,
        "baseCurrency": "MUR",
        "baseName": "Mauritian Rupee",
        "targetCurrency": "MNT",
        "targetName": "Mongolian togrog",
        "exchangeRate": "71.150848",
        "inverseRate": "0.014055",
        "inverseDescription": "1 Mongolian togrog = 0.014055 Mauritian Rupee"
      },
      {
        "title": "1 MUR = 3.216872 VUV",
        "link": "http://www.floatrates.com/mur/vuv/",
        "description": "1 Mauritian Rupee = 3.216872 Vanuatu vatu",
        "pubDate": null,
        "baseCurrency": "MUR",
        "baseName": "Mauritian Rupee",
        "targetCurrency": "VUV",
        "targetName": "Vanuatu vatu",
        "exchangeRate": "3.216872",
        "inverseRate": "0.310861",
        "inverseDescription": "1 Vanuatu vatu = 0.310861 Mauritian Rupee"
      },
      {
        "title": "1 MUR = 0.046982 BAM",
        "link": "http://www.floatrates.com/mur/bam/",
        "description": "1 Mauritian Rupee = 0.046982 Bosnia and Herzegovina convertible mark",
        "pubDate": null,
        "baseCurrency": "MUR",
        "baseName": "Mauritian Rupee",
        "targetCurrency": "BAM",
        "targetName": "Bosnia and Herzegovina convertible mark",
        "exchangeRate": "0.046982",
        "inverseRate": "21.284595",
        "inverseDescription": "1 Bosnia and Herzegovina convertible mark = 21.284595 Mauritian Rupee"
      },
      {
        "title": "1 MUR = 1.054311 MRO",
        "link": "http://www.floatrates.com/mur/mro/",
        "description": "1 Mauritian Rupee = 1.054311 Mauritanian Ouguiya",
        "pubDate": null,
        "baseCurrency": "MUR",
        "baseName": "Mauritian Rupee",
        "targetCurrency": "MRO",
        "targetName": "Mauritanian Ouguiya",
        "exchangeRate": "1.054311",
        "inverseRate": "0.948487",
        "inverseDescription": "1 Mauritanian Ouguiya = 0.948487 Mauritian Rupee"
      }
    ]
  }
}