{
  "channel": {
    "title": "XML Historical Foreign Exchange Rates for Icelandic Krona (ISK) (13 May 2015)",
    "link": "http://www.floatrates.com/currency/isk/",
    "xmlLink": "http://www.floatrates.com/daily/isk.xml",
    "description": "XML historical foreign exchange rates for Icelandic Krona (ISK) from the Float Rates. Published at 13 May 2015.",
    "language": "en",
    "baseCurrency": "ISK",
    "pubDate": "Wed, 13 May 2015",
    "lastBuildDate": "Wed, 13 May 2015",
    "item": [
      {
        "title": "1 ISK = 0.007619 USD",
        "link": "http://www.floatrates.com/isk/usd/",
        "description": "1 Icelandic Krona = 0.007619 U.S. Dollar",
        "pubDate": null,
        "baseCurrency": "ISK",
        "baseName": "Icelandic Krona",
        "targetCurrency": "USD",
        "targetName": "U.S. Dollar",
        "exchangeRate": "0.007619",
        "inverseRate": "131.242538",
        "inverseDescription": "1 U.S. Dollar = 131.242538 Icelandic Krona"
      },
      {
        "title": "1 ISK = 0.068201 ARS",
        "link": "http://www.floatrates.com/isk/ars/",
        "description": "1 Icelandic Krona = 0.068201 Argentine Peso",
        "pubDate": null,
        "baseCurrency": "ISK",
        "baseName": "Icelandic Krona",
        "targetCurrency": "ARS",
        "targetName": "Argentine Peso",
        "exchangeRate": "0.068201",
        "inverseRate": "14.662441",
        "inverseDescription": "1 Argentine Peso = 14.662441 Icelandic Krona"
      },
      {
        "title": "1 ISK = 0.009504 AUD",
        "link": "http://www.floatrates.com/isk/aud/",
        "description": "1 Icelandic Krona = 0.009504 Australian Dollar",
        "pubDate": null,
        "baseCurrency": "ISK",
        "baseName": "Icelandic Krona",
        "targetCurrency": "AUD",
        "targetName": "Australian Dollar",
        "exchangeRate": "0.009504",
        "inverseRate": "105.217172",
        "inverseDescription": "1 Australian Dollar = 105.217172 Icelandic Krona"
      },
      {
        "title": "1 ISK = 0.007630 BSD",
        "link": "http://www.floatrates.com/isk/bsd/",
        "description": "1 Icelandic Krona = 0.007630 Bahamian Dollar",
        "pubDate": null,
        "baseCurrency": "ISK",
        "baseName": "Icelandic Krona",
        "targetCurrency": "BSD",
        "targetName": "Bahamian Dollar",
        "exchangeRate": "0.007630",
        "inverseRate": "131.054332",
        "inverseDescription": "1 Bahamian Dollar = 131.054332 Icelandic Krona"
      },
      {
        "title": "1 ISK = 0.023030 BRL",
        "link": "http://www.floatrates.com/isk/brl/",
        "description": "1 Icelandic Krona = 0.023030 Brazilian Real",
        "pubDate": null,
        "baseCurrency": "ISK",
        "baseName": "Icelandic Krona",
        "targetCurrency": "BRL",
        "targetName": "Brazilian Real",
        "exchangeRate": "0.023030",
        "inverseRate": "43.422336",
        "inverseDescription": "1 Brazilian Real = 43.422336 Icelandic Krona"
      },
      {
        "title": "1 ISK = 4.400857 XAF",
        "link": "http://www.floatrates.com/isk/xaf/",
        "description": "1 Icelandic Krona = 4.400857 Central African CFA Franc",
        "pubDate": null,
        "baseCurrency": "ISK",
        "baseName": "Icelandic Krona",
        "targetCurrency": "XAF",
        "targetName": "Central African CFA Franc",
        "exchangeRate": "4.400857",
        "inverseRate": "0.227228",
        "inverseDescription": "1 Central African CFA Franc = 0.227228 Icelandic Krona"
      },
      {
        "title": "1 ISK = 0.800577 XPF",
        "link": "http://www.floatrates.com/isk/xpf/",
        "description": "1 Icelandic Krona = 0.800577 CFP Franc",
        "pubDate": null,
        "baseCurrency": "ISK",
        "baseName": "Icelandic Krona",
        "targetCurrency": "XPF",
        "targetName": "CFP Franc",
        "exchangeRate": "0.800577",
        "inverseRate": "1.249099",
        "inverseDescription": "1 CFP Franc = 1.249099 Icelandic Krona"
      },
      {
        "title": "1 ISK = 4.607097 CLP",
        "link": "http://www.floatrates.com/isk/clp/",
        "description": "1 Icelandic Krona = 4.607097 Chilean Peso",
        "pubDate": null,
        "baseCurrency": "ISK",
        "baseName": "Icelandic Krona",
        "targetCurrency": "CLP",
        "targetName": "Chilean Peso",
        "exchangeRate": "4.607097",
        "inverseRate": "0.217056",
        "inverseDescription": "1 Chilean Peso = 0.217056 Icelandic Krona"
      },
      {
        "title": "1 ISK = 0.047106 CNY",
        "link": "http://www.floatrates.com/isk/cny/",
        "description": "1 Icelandic Krona = 0.047106 Chinese Yuan",
        "pubDate": null,
        "baseCurrency": "ISK",
        "baseName": "Icelandic Krona",
        "targetCurrency": "CNY",
        "targetName": "Chinese Yuan",
        "exchangeRate": "0.047106",
        "inverseRate": "21.228769",
        "inverseDescription": "1 Chinese Yuan = 21.228769 Icelandic Krona"
      },
      {
        "title": "1 ISK = 18.175220 COP",
        "link": "http://www.floatrates.com/isk/cop/",
        "description": "1 Icelandic Krona = 18.175220 Colombian Peso",
        "pubDate": null,
        "baseCurrency": "ISK",
        "baseName": "Icelandic Krona",
        "targetCurrency": "COP",
        "targetName": "Colombian Peso",
        "exchangeRate": "18.175220",
        "inverseRate": "0.055020",
        "inverseDescription": "1 Colombian Peso = 0.055020 Icelandic Krona"
      },
      {
        "title": "1 ISK = 0.050901 HRK",
        "link": "http://www.floatrates.com/isk/hrk/",
        "description": "1 Icelandic Krona = 0.050901 Croatian Kuna",
        "pubDate": null,
        "baseCurrency": "ISK",
        "baseName": "Icelandic Krona",
        "targetCurrency": "HRK",
        "targetName": "Croatian Kuna",
        "exchangeRate": "0.050901",
        "inverseRate": "19.646089",
        "inverseDescription": "1 Croatian Kuna = 19.646089 Icelandic Krona"
      },
      {
        "title": "1 ISK = 0.185549 CZK",
        "link": "http://www.floatrates.com/isk/czk/",
        "description": "1 Icelandic Krona = 0.185549 Czech Koruna",
        "pubDate": null,
        "baseCurrency": "ISK",
        "baseName": "Icelandic Krona",
        "targetCurrency": "CZK",
        "targetName": "Czech Koruna",
        "exchangeRate": "0.185549",
        "inverseRate": "5.389404",
        "inverseDescription": "1 Czech Koruna = 5.389404 Icelandic Krona"
      },
      {
        "title": "1 ISK = 0.050480 DKK",
        "link": "http://www.floatrates.com/isk/dkk/",
        "description": "1 Icelandic Krona = 0.050480 Danish Krone",
        "pubDate": null,
        "baseCurrency": "ISK",
        "baseName": "Icelandic Krona",
        "targetCurrency": "DKK",
        "targetName": "Danish Krone",
        "exchangeRate": "0.050480",
        "inverseRate": "19.809978",
        "inverseDescription": "1 Danish Krone = 19.809978 Icelandic Krona"
      },
      {
        "title": "1 ISK = 0.020523 XCD",
        "link": "http://www.floatrates.com/isk/xcd/",
        "description": "1 Icelandic Krona = 0.020523 East Caribbean Dollar",
        "pubDate": null,
        "baseCurrency": "ISK",
        "baseName": "Icelandic Krona",
        "targetCurrency": "XCD",
        "targetName": "East Caribbean Dollar",
        "exchangeRate": "0.020523",
        "inverseRate": "48.725403",
        "inverseDescription": "1 East Caribbean Dollar = 48.725403 Icelandic Krona"
      },
      {
        "title": "1 ISK = 0.006771 EUR",
        "link": "http://www.floatrates.com/isk/eur/",
        "description": "1 Icelandic Krona = 0.006771 Euro",
        "pubDate": null,
        "baseCurrency": "ISK",
        "baseName": "Icelandic Krona",
        "targetCurrency": "EUR",
        "targetName": "Euro",
        "exchangeRate": "0.006771",
        "inverseRate": "147.679224",
        "inverseDescription": "1 Euro = 147.679224 Icelandic Krona"
      },
      {
        "title": "1 ISK = 0.015445 FJD",
        "link": "http://www.floatrates.com/isk/fjd/",
        "description": "1 Icelandic Krona = 0.015445 Fiji Dollar",
        "pubDate": null,
        "baseCurrency": "ISK",
        "baseName": "Icelandic Krona",
        "targetCurrency": "FJD",
        "targetName": "Fiji Dollar",
        "exchangeRate": "0.015445",
        "inverseRate": "64.745699",
        "inverseDescription": "1 Fiji Dollar = 64.745699 Icelandic Krona"
      },
      {
        "title": "1 ISK = 0.030174 GHS",
        "link": "http://www.floatrates.com/isk/ghs/",
        "description": "1 Icelandic Krona = 0.030174 Ghanaian Cedi",
        "pubDate": null,
        "baseCurrency": "ISK",
        "baseName": "Icelandic Krona",
        "targetCurrency": "GHS",
        "targetName": "Ghanaian Cedi",
        "exchangeRate": "0.030174",
        "inverseRate": "33.140813",
        "inverseDescription": "1 Ghanaian Cedi = 33.140813 Icelandic Krona"
      },
      {
        "title": "1 ISK = 0.059912 GTQ",
        "link": "http://www.floatrates.com/isk/gtq/",
        "description": "1 Icelandic Krona = 0.059912 Guatemalan Quetzal",
        "pubDate": null,
        "baseCurrency": "ISK",
        "baseName": "Icelandic Krona",
        "targetCurrency": "GTQ",
        "targetName": "Guatemalan Quetzal",
        "exchangeRate": "0.059912",
        "inverseRate": "16.691211",
        "inverseDescription": "1 Guatemalan Quetzal = 16.691211 Icelandic Krona"
      },
      {
        "title": "1 ISK = 0.167313 HNL",
        "link": "http://www.floatrates.com/isk/hnl/",
        "description": "1 Icelandic Krona = 0.167313 Honduran Lempira",
        "pubDate": null,
        "baseCurrency": "ISK",
        "baseName": "Icelandic Krona",
        "targetCurrency": "HNL",
        "targetName": "Honduran Lempira",
        "exchangeRate": "0.167313",
        "inverseRate": "5.976819",
        "inverseDescription": "1 Honduran Lempira = 5.976819 Icelandic Krona"
      },
      {
        "title": "1 ISK = 0.059069 HKD",
        "link": "http://www.floatrates.com/isk/hkd/",
        "description": "1 Icelandic Krona = 0.059069 Hong Kong Dollar",
        "pubDate": null,
        "baseCurrency": "ISK",
        "baseName": "Icelandic Krona",
        "targetCurrency": "HKD",
        "targetName": "Hong Kong Dollar",
        "exchangeRate": "0.059069",
        "inverseRate": "16.929294",
        "inverseDescription": "1 Hong Kong Dollar = 16.929294 Icelandic Krona"
      },
      {
        "title": "1 ISK = 2.071437 HUF",
        "link": "http://www.floatrates.com/isk/huf/",
        "description": "1 Icelandic Krona = 2.071437 Hungarian Forint",
        "pubDate": null,
        "baseCurrency": "ISK",
        "baseName": "Icelandic Krona",
        "targetCurrency": "HUF",
        "targetName": "Hungarian Forint",
        "exchangeRate": "2.071437",
        "inverseRate": "0.482757",
        "inverseDescription": "1 Hungarian Forint = 0.482757 Icelandic Krona"
      },
      {
        "title": "1 ISK = 1.000000 ISK",
        "link": "http://www.floatrates.com/isk/isk/",
        "description": "1 Icelandic Krona = 1.000000 Icelandic Krona",
        "pubDate": null,
        "baseCurrency": "ISK",
        "baseName": "Icelandic Krona",
        "targetCurrency": "ISK",
        "targetName": "Icelandic Krona",
        "exchangeRate": "1.000000",
        "inverseRate": "1.000000",
        "inverseDescription": "1 Icelandic Krona = 1.000000 Icelandic Krona"
      },
      {
        "title": "1 ISK = 0.488359 INR",
        "link": "http://www.floatrates.com/isk/inr/",
        "description": "1 Icelandic Krona = 0.488359 Indian Rupee",
        "pubDate": null,
        "baseCurrency": "ISK",
        "baseName": "Icelandic Krona",
        "targetCurrency": "INR",
        "targetName": "Indian Rupee",
        "exchangeRate": "0.488359",
        "inverseRate": "2.047673",
        "inverseDescription": "1 Indian Rupee = 2.047673 Icelandic Krona"
      },
      {
        "title": "1 ISK = 100.324833 IDR",
        "link": "http://www.floatrates.com/isk/idr/",
        "description": "1 Icelandic Krona = 100.324833 Indonesian Rupiah",
        "pubDate": null,
        "baseCurrency": "ISK",
        "baseName": "Icelandic Krona",
        "targetCurrency": "IDR",
        "targetName": "Indonesian Rupiah",
        "exchangeRate": "100.324833",
        "inverseRate": "0.009968",
        "inverseDescription": "1 Indonesian Rupiah = 0.009968 Icelandic Krona"
      },
      {
        "title": "1 ISK = 0.029311 ILS",
        "link": "http://www.floatrates.com/isk/ils/",
        "description": "1 Icelandic Krona = 0.029311 Israeli New Sheqel",
        "pubDate": null,
        "baseCurrency": "ISK",
        "baseName": "Icelandic Krona",
        "targetCurrency": "ILS",
        "targetName": "Israeli New Sheqel",
        "exchangeRate": "0.029311",
        "inverseRate": "34.116588",
        "inverseDescription": "1 Israeli New Sheqel = 34.116588 Icelandic Krona"
      },
      {
        "title": "1 ISK = 0.882727 JMD",
        "link": "http://www.floatrates.com/isk/jmd/",
        "description": "1 Icelandic Krona = 0.882727 Jamaican Dollar",
        "pubDate": null,
        "baseCurrency": "ISK",
        "baseName": "Icelandic Krona",
        "targetCurrency": "JMD",
        "targetName": "Jamaican Dollar",
        "exchangeRate": "0.882727",
        "inverseRate": "1.132853",
        "inverseDescription": "1 Jamaican Dollar = 1.132853 Icelandic Krona"
      },
      {
        "title": "1 ISK = 0.911700 JPY",
        "link": "http://www.floatrates.com/isk/jpy/",
        "description": "1 Icelandic Krona = 0.911700 Japanese Yen",
        "pubDate": null,
        "baseCurrency": "ISK",
        "baseName": "Icelandic Krona",
        "targetCurrency": "JPY",
        "targetName": "Japanese Yen",
        "exchangeRate": "0.911700",
        "inverseRate": "1.096852",
        "inverseDescription": "1 Japanese Yen = 1.096852 Icelandic Krona"
      },
      {
        "title": "1 ISK = 0.027460 MYR",
        "link": "http://www.floatrates.com/isk/myr/",
        "description": "1 Icelandic Krona = 0.027460 Malaysian Ringgit",
        "pubDate": null,
        "baseCurrency": "ISK",
        "baseName": "Icelandic Krona",
        "targetCurrency": "MYR",
        "targetName": "Malaysian Ringgit",
        "exchangeRate": "0.027460",
        "inverseRate": "36.416188",
        "inverseDescription": "1 Malaysian Ringgit = 36.416188 Icelandic Krona"
      },
      {
        "title": "1 ISK = 0.116458 MXN",
        "link": "http://www.floatrates.com/isk/mxn/",
        "description": "1 Icelandic Krona = 0.116458 Mexican Peso",
        "pubDate": null,
        "baseCurrency": "ISK",
        "baseName": "Icelandic Krona",
        "targetCurrency": "MXN",
        "targetName": "Mexican Peso",
        "exchangeRate": "0.116458",
        "inverseRate": "8.586805",
        "inverseDescription": "1 Mexican Peso = 8.586805 Icelandic Krona"
      },
      {
        "title": "1 ISK = 0.073301 MAD",
        "link": "http://www.floatrates.com/isk/mad/",
        "description": "1 Icelandic Krona = 0.073301 Moroccan Dirham",
        "pubDate": null,
        "baseCurrency": "ISK",
        "baseName": "Icelandic Krona",
        "targetCurrency": "MAD",
        "targetName": "Moroccan Dirham",
        "exchangeRate": "0.073301",
        "inverseRate": "13.642458",
        "inverseDescription": "1 Moroccan Dirham = 13.642458 Icelandic Krona"
      },
      {
        "title": "1 ISK = 8.289613 MMK",
        "link": "http://www.floatrates.com/isk/mmk/",
        "description": "1 Icelandic Krona = 8.289613 Myanma Kyat",
        "pubDate": null,
        "baseCurrency": "ISK",
        "baseName": "Icelandic Krona",
        "targetCurrency": "MMK",
        "targetName": "Myanma Kyat",
        "exchangeRate": "8.289613",
        "inverseRate": "0.120633",
        "inverseDescription": "1 Myanma Kyat = 0.120633 Icelandic Krona"
      },
      {
        "title": "1 ISK = 0.013430 ANG",
        "link": "http://www.floatrates.com/isk/ang/",
        "description": "1 Icelandic Krona = 0.013430 Neth. Antillean Guilder",
        "pubDate": null,
        "baseCurrency": "ISK",
        "baseName": "Icelandic Krona",
        "targetCurrency": "ANG",
        "targetName": "Neth. Antillean Guilder",
        "exchangeRate": "0.013430",
        "inverseRate": "74.461071",
        "inverseDescription": "1 Neth. Antillean Guilder = 74.461071 Icelandic Krona"
      },
      {
        "title": "1 ISK = 0.010275 NZD",
        "link": "http://www.floatrates.com/isk/nzd/",
        "description": "1 Icelandic Krona = 0.010275 New Zealand Dollar",
        "pubDate": null,
        "baseCurrency": "ISK",
        "baseName": "Icelandic Krona",
        "targetCurrency": "NZD",
        "targetName": "New Zealand Dollar",
        "exchangeRate": "0.010275",
        "inverseRate": "97.325481",
        "inverseDescription": "1 New Zealand Dollar = 97.325481 Icelandic Krona"
      },
      {
        "title": "1 ISK = 0.056560 NOK",
        "link": "http://www.floatrates.com/isk/nok/",
        "description": "1 Icelandic Krona = 0.056560 Norwegian Krone",
        "pubDate": null,
        "baseCurrency": "ISK",
        "baseName": "Icelandic Krona",
        "targetCurrency": "NOK",
        "targetName": "Norwegian Krone",
        "exchangeRate": "0.056560",
        "inverseRate": "17.680268",
        "inverseDescription": "1 Norwegian Krone = 17.680268 Icelandic Krona"
      },
      {
        "title": "1 ISK = 0.776536 PKR",
        "link": "http://www.floatrates.com/isk/pkr/",
        "description": "1 Icelandic Krona = 0.776536 Pakistani Rupee",
        "pubDate": null,
        "baseCurrency": "ISK",
        "baseName": "Icelandic Krona",
        "targetCurrency": "PKR",
        "targetName": "Pakistani Rupee",
        "exchangeRate": "0.776536",
        "inverseRate": "1.287771",
        "inverseDescription": "1 Pakistani Rupee = 1.287771 Icelandic Krona"
      },
      {
        "title": "1 ISK = 0.007630 PAB",
        "link": "http://www.floatrates.com/isk/pab/",
        "description": "1 Icelandic Krona = 0.007630 Panamanian Balboa",
        "pubDate": null,
        "baseCurrency": "ISK",
        "baseName": "Icelandic Krona",
        "targetCurrency": "PAB",
        "targetName": "Panamanian Balboa",
        "exchangeRate": "0.007630",
        "inverseRate": "131.054332",
        "inverseDescription": "1 Panamanian Balboa = 131.054332 Icelandic Krona"
      },
      {
        "title": "1 ISK = 0.024053 PEN",
        "link": "http://www.floatrates.com/isk/pen/",
        "description": "1 Icelandic Krona = 0.024053 Peruvian Nuevo Sol",
        "pubDate": null,
        "baseCurrency": "ISK",
        "baseName": "Icelandic Krona",
        "targetCurrency": "PEN",
        "targetName": "Peruvian Nuevo Sol",
        "exchangeRate": "0.024053",
        "inverseRate": "41.574898",
        "inverseDescription": "1 Peruvian Nuevo Sol = 41.574898 Icelandic Krona"
      },
      {
        "title": "1 ISK = 0.340507 PHP",
        "link": "http://www.floatrates.com/isk/php/",
        "description": "1 Icelandic Krona = 0.340507 Philippine Peso",
        "pubDate": null,
        "baseCurrency": "ISK",
        "baseName": "Icelandic Krona",
        "targetCurrency": "PHP",
        "targetName": "Philippine Peso",
        "exchangeRate": "0.340507",
        "inverseRate": "2.936795",
        "inverseDescription": "1 Philippine Peso = 2.936795 Icelandic Krona"
      },
      {
        "title": "1 ISK = 0.027602 PLN",
        "link": "http://www.floatrates.com/isk/pln/",
        "description": "1 Icelandic Krona = 0.027602 Polish Zloty",
        "pubDate": null,
        "baseCurrency": "ISK",
        "baseName": "Icelandic Krona",
        "targetCurrency": "PLN",
        "targetName": "Polish Zloty",
        "exchangeRate": "0.027602",
        "inverseRate": "36.229182",
        "inverseDescription": "1 Polish Zloty = 36.229182 Icelandic Krona"
      },
      {
        "title": "1 ISK = 0.030064 RON",
        "link": "http://www.floatrates.com/isk/ron/",
        "description": "1 Icelandic Krona = 0.030064 Romanian New Leu",
        "pubDate": null,
        "baseCurrency": "ISK",
        "baseName": "Icelandic Krona",
        "targetCurrency": "RON",
        "targetName": "Romanian New Leu",
        "exchangeRate": "0.030064",
        "inverseRate": "33.262394",
        "inverseDescription": "1 Romanian New Leu = 33.262394 Icelandic Krona"
      },
      {
        "title": "1 ISK = 0.376126 RUB",
        "link": "http://www.floatrates.com/isk/rub/",
        "description": "1 Icelandic Krona = 0.376126 Russian Rouble",
        "pubDate": null,
        "baseCurrency": "ISK",
        "baseName": "Icelandic Krona",
        "targetCurrency": "RUB",
        "targetName": "Russian Rouble",
        "exchangeRate": "0.376126",
        "inverseRate": "2.658686",
        "inverseDescription": "1 Russian Rouble = 2.658686 Icelandic Krona"
      },
      {
        "title": "1 ISK = 0.808712 RSD",
        "link": "http://www.floatrates.com/isk/rsd/",
        "description": "1 Icelandic Krona = 0.808712 Serbian Dinar",
        "pubDate": null,
        "baseCurrency": "ISK",
        "baseName": "Icelandic Krona",
        "targetCurrency": "RSD",
        "targetName": "Serbian Dinar",
        "exchangeRate": "0.808712",
        "inverseRate": "1.236534",
        "inverseDescription": "1 Serbian Dinar = 1.236534 Icelandic Krona"
      },
      {
        "title": "1 ISK = 0.010147 SGD",
        "link": "http://www.floatrates.com/isk/sgd/",
        "description": "1 Icelandic Krona = 0.010147 Singapore Dollar",
        "pubDate": null,
        "baseCurrency": "ISK",
        "baseName": "Icelandic Krona",
        "targetCurrency": "SGD",
        "targetName": "Singapore Dollar",
        "exchangeRate": "0.010147",
        "inverseRate": "98.550990",
        "inverseDescription": "1 Singapore Dollar = 98.550990 Icelandic Krona"
      },
      {
        "title": "1 ISK = 0.090913 ZAR",
        "link": "http://www.floatrates.com/isk/zar/",
        "description": "1 Icelandic Krona = 0.090913 South African Rand",
        "pubDate": null,
        "baseCurrency": "ISK",
        "baseName": "Icelandic Krona",
        "targetCurrency": "ZAR",
        "targetName": "South African Rand",
        "exchangeRate": "0.090913",
        "inverseRate": "10.999480",
        "inverseDescription": "1 South African Rand = 10.999480 Icelandic Krona"
      },
      {
        "title": "1 ISK = 8.352307 KRW",
        "link": "http://www.floatrates.com/isk/krw/",
        "description": "1 Icelandic Krona = 8.352307 South Korean Won",
        "pubDate": null,
        "baseCurrency": "ISK",
        "baseName": "Icelandic Krona",
        "targetCurrency": "KRW",
        "targetName": "South Korean Won",
        "exchangeRate": "8.352307",
        "inverseRate": "0.119727",
        "inverseDescription": "1 South Korean Won = 0.119727 Icelandic Krona"
      },
      {
        "title": "1 ISK = 1.018645 LKR",
        "link": "http://www.floatrates.com/isk/lkr/",
        "description": "1 Icelandic Krona = 1.018645 Sri Lanka Rupee",
        "pubDate": null,
        "baseCurrency": "ISK",
        "baseName": "Icelandic Krona",
        "targetCurrency": "LKR",
        "targetName": "Sri Lanka Rupee",
        "exchangeRate": "1.018645",
        "inverseRate": "0.981697",
        "inverseDescription": "1 Sri Lanka Rupee = 0.981697 Icelandic Krona"
      },
      {
        "title": "1 ISK = 0.063066 SEK",
        "link": "http://www.floatrates.com/isk/sek/",
        "description": "1 Icelandic Krona = 0.063066 Swedish Krona",
        "pubDate": null,
        "baseCurrency": "ISK",
        "baseName": "Icelandic Krona",
        "targetCurrency": "SEK",
        "targetName": "Swedish Krona",
        "exchangeRate": "0.063066",
        "inverseRate": "15.856476",
        "inverseDescription": "1 Swedish Krona = 15.856476 Icelandic Krona"
      },
      {
        "title": "1 ISK = 0.007052 CHF",
        "link": "http://www.floatrates.com/isk/chf/",
        "description": "1 Icelandic Krona = 0.007052 Swiss Franc",
        "pubDate": null,
        "baseCurrency": "ISK",
        "baseName": "Icelandic Krona",
        "targetCurrency": "CHF",
        "targetName": "Swiss Franc",
        "exchangeRate": "0.007052",
        "inverseRate": "141.804550",
        "inverseDescription": "1 Swiss Franc = 141.804550 Icelandic Krona"
      },
      {
        "title": "1 ISK = 0.233727 TWD",
        "link": "http://www.floatrates.com/isk/twd/",
        "description": "1 Icelandic Krona = 0.233727 New Taiwan Dollar",
        "pubDate": null,
        "baseCurrency": "ISK",
        "baseName": "Icelandic Krona",
        "targetCurrency": "TWD",
        "targetName": "New Taiwan Dollar",
        "exchangeRate": "0.233727",
        "inverseRate": "4.278505",
        "inverseDescription": "1 New Taiwan Dollar  = 4.278505 Icelandic Krona"
      },
      {
        "title": "1 ISK = 0.256322 THB",
        "link": "http://www.floatrates.com/isk/thb/",
        "description": "1 Icelandic Krona = 0.256322 Thai Baht",
        "pubDate": null,
        "baseCurrency": "ISK",
        "baseName": "Icelandic Krona",
        "targetCurrency": "THB",
        "targetName": "Thai Baht",
        "exchangeRate": "0.256322",
        "inverseRate": "3.901341",
        "inverseDescription": "1 Thai Baht = 3.901341 Icelandic Krona"
      },
      {
        "title": "1 ISK = 0.048332 TTD",
        "link": "http://www.floatrates.com/isk/ttd/",
        "description": "1 Icelandic Krona = 0.048332 Trinidad Tobago Dollar",
        "pubDate": null,
        "baseCurrency": "ISK",
        "baseName": "Icelandic Krona",
        "targetCurrency": "TTD",
        "targetName": "Trinidad Tobago Dollar",
        "exchangeRate": "0.048332",
        "inverseRate": "20.690150",
        "inverseDescription": "1 Trinidad Tobago Dollar = 20.690150 Icelandic Krona"
      },
      {
        "title": "1 ISK = 0.014604 TND",
        "link": "http://www.floatrates.com/isk/tnd/",
        "description": "1 Icelandic Krona = 0.014604 Tunisian Dinar",
        "pubDate": null,
        "baseCurrency": "ISK",
        "baseName": "Icelandic Krona",
        "targetCurrency": "TND",
        "targetName": "Tunisian Dinar",
        "exchangeRate": "0.014604",
        "inverseRate": "68.473237",
        "inverseDescription": "1 Tunisian Dinar = 68.473237 Icelandic Krona"
      },
      {
        "title": "1 ISK = 0.020114 TRY",
        "link": "http://www.floatrates.com/isk/try/",
        "description": "1 Icelandic Krona = 0.020114 Turkish Lira",
        "pubDate": null,
        "baseCurrency": "ISK",
        "baseName": "Icelandic Krona",
        "targetCurrency": "TRY",
        "targetName": "Turkish Lira",
        "exchangeRate": "0.020114",
        "inverseRate": "49.716977",
        "inverseDescription": "1 Turkish Lira = 49.716977 Icelandic Krona"
      },
      {
        "title": "1 ISK = 0.027996 AED",
        "link": "http://www.floatrates.com/isk/aed/",
        "description": "1 Icelandic Krona = 0.027996 U.A.E Dirham",
        "pubDate": null,
        "baseCurrency": "ISK",
        "baseName": "Icelandic Krona",
        "targetCurrency": "AED",
        "targetName": "U.A.E Dirham",
        "exchangeRate": "0.027996",
        "inverseRate": "35.719746",
        "inverseDescription": "1 U.A.E Dirham = 35.719746 Icelandic Krona"
      },
      {
        "title": "1 ISK = 0.004853 GBP",
        "link": "http://www.floatrates.com/isk/gbp/",
        "description": "1 Icelandic Krona = 0.004853 U.K. Pound Sterling",
        "pubDate": null,
        "baseCurrency": "ISK",
        "baseName": "Icelandic Krona",
        "targetCurrency": "GBP",
        "targetName": "U.K. Pound Sterling",
        "exchangeRate": "0.004853",
        "inverseRate": "206.038090",
        "inverseDescription": "1 U.K. Pound Sterling = 206.038090 Icelandic Krona"
      },
      {
        "title": "1 ISK = 0.047975 VEF",
        "link": "http://www.floatrates.com/isk/vef/",
        "description": "1 Icelandic Krona = 0.047975 Venezuelan Bolivar (till 20 August 2018)",
        "pubDate": null,
        "baseCurrency": "ISK",
        "baseName": "Icelandic Krona",
        "targetCurrency": "VEF",
        "targetName": "Venezuelan Bolivar (till 20 August 2018)",
        "exchangeRate": "0.047975",
        "inverseRate": "20.843993",
        "inverseDescription": "1 Venezuelan Bolivar (till 20 August 2018) = 20.843993 Icelandic Krona"
      },
      {
        "title": "1 ISK = 165.623016 VND",
        "link": "http://www.floatrates.com/isk/vnd/",
        "description": "1 Icelandic Krona = 165.623016 Vietnamese Dong",
        "pubDate": null,
        "baseCurrency": "ISK",
        "baseName": "Icelandic Krona",
        "targetCurrency": "VND",
        "targetName": "Vietnamese Dong",
        "exchangeRate": "165.623016",
        "inverseRate": "0.006038",
        "inverseDescription": "1 Vietnamese Dong = 0.006038 Icelandic Krona"
      },
      {
        "title": "1 ISK = 0.009128 CAD",
        "link": "http://www.floatrates.com/isk/cad/",
        "description": "1 Icelandic Krona = 0.009128 Canadian Dollar",
        "pubDate": null,
        "baseCurrency": "ISK",
        "baseName": "Icelandic Krona",
        "targetCurrency": "CAD",
        "targetName": "Canadian Dollar",
        "exchangeRate": "0.009128",
        "inverseRate": "109.554165",
        "inverseDescription": "1 Canadian Dollar = 109.554165 Icelandic Krona"
      },
      {
        "title": "1 ISK = 0.020621 PGK",
        "link": "http://www.floatrates.com/isk/pgk/",
        "description": "1 Icelandic Krona = 0.020621 Papua New Guinean kina",
        "pubDate": null,
        "baseCurrency": "ISK",
        "baseName": "Icelandic Krona",
        "targetCurrency": "PGK",
        "targetName": "Papua New Guinean kina",
        "exchangeRate": "0.020621",
        "inverseRate": "48.493150",
        "inverseDescription": "1 Papua New Guinean kina = 48.493150 Icelandic Krona"
      },
      {
        "title": "1 ISK = 0.007991 AZN",
        "link": "http://www.floatrates.com/isk/azn/",
        "description": "1 Icelandic Krona = 0.007991 Azerbaijan Manat",
        "pubDate": null,
        "baseCurrency": "ISK",
        "baseName": "Icelandic Krona",
        "targetCurrency": "AZN",
        "targetName": "Azerbaijan Manat",
        "exchangeRate": "0.007991",
        "inverseRate": "125.141886",
        "inverseDescription": "1 Azerbaijan Manat = 125.141886 Icelandic Krona"
      },
      {
        "title": "1 ISK = 3.664212 AMD",
        "link": "http://www.floatrates.com/isk/amd/",
        "description": "1 Icelandic Krona = 3.664212 Armenia Dram",
        "pubDate": null,
        "baseCurrency": "ISK",
        "baseName": "Icelandic Krona",
        "targetCurrency": "AMD",
        "targetName": "Armenia Dram",
        "exchangeRate": "3.664212",
        "inverseRate": "0.272910",
        "inverseDescription": "1 Armenia Dram = 0.272910 Icelandic Krona"
      },
      {
        "title": "1 ISK = 108.527088 BYR",
        "link": "http://www.floatrates.com/isk/byr/",
        "description": "1 Icelandic Krona = 108.527088 Belarussian Ruble",
        "pubDate": null,
        "baseCurrency": "ISK",
        "baseName": "Icelandic Krona",
        "targetCurrency": "BYR",
        "targetName": "Belarussian Ruble",
        "exchangeRate": "108.527088",
        "inverseRate": "0.009214",
        "inverseDescription": "1 Belarussian Ruble = 0.009214 Icelandic Krona"
      },
      {
        "title": "1 ISK = 0.013280 BGN",
        "link": "http://www.floatrates.com/isk/bgn/",
        "description": "1 Icelandic Krona = 0.013280 Bulgarian Lev",
        "pubDate": null,
        "baseCurrency": "ISK",
        "baseName": "Icelandic Krona",
        "targetCurrency": "BGN",
        "targetName": "Bulgarian Lev",
        "exchangeRate": "0.013280",
        "inverseRate": "75.303484",
        "inverseDescription": "1 Bulgarian Lev = 75.303484 Icelandic Krona"
      },
      {
        "title": "1 ISK = 1.415734 KZT",
        "link": "http://www.floatrates.com/isk/kzt/",
        "description": "1 Icelandic Krona = 1.415734 Kazakhstani Tenge",
        "pubDate": null,
        "baseCurrency": "ISK",
        "baseName": "Icelandic Krona",
        "targetCurrency": "KZT",
        "targetName": "Kazakhstani Tenge",
        "exchangeRate": "1.415734",
        "inverseRate": "0.706347",
        "inverseDescription": "1 Kazakhstani Tenge = 0.706347 Icelandic Krona"
      },
      {
        "title": "1 ISK = 0.449645 KGS",
        "link": "http://www.floatrates.com/isk/kgs/",
        "description": "1 Icelandic Krona = 0.449645 Kyrgyzstan Som",
        "pubDate": null,
        "baseCurrency": "ISK",
        "baseName": "Icelandic Krona",
        "targetCurrency": "KGS",
        "targetName": "Kyrgyzstan Som",
        "exchangeRate": "0.449645",
        "inverseRate": "2.223975",
        "inverseDescription": "1 Kyrgyzstan Som = 2.223975 Icelandic Krona"
      },
      {
        "title": "1 ISK = 0.135353 MDL",
        "link": "http://www.floatrates.com/isk/mdl/",
        "description": "1 Icelandic Krona = 0.135353 Moldova Lei",
        "pubDate": null,
        "baseCurrency": "ISK",
        "baseName": "Icelandic Krona",
        "targetCurrency": "MDL",
        "targetName": "Moldova Lei",
        "exchangeRate": "0.135353",
        "inverseRate": "7.388093",
        "inverseDescription": "1 Moldova Lei = 7.388093 Icelandic Krona"
      },
      {
        "title": "1 ISK = 0.026666 TMT",
        "link": "http://www.floatrates.com/isk/tmt/",
        "description": "1 Icelandic Krona = 0.026666 New Turkmenistan Manat",
        "pubDate": null,
        "baseCurrency": "ISK",
        "baseName": "Icelandic Krona",
        "targetCurrency": "TMT",
        "targetName": "New Turkmenistan Manat",
        "exchangeRate": "0.026666",
        "inverseRate": "37.500499",
        "inverseDescription": "1 New Turkmenistan Manat = 37.500499 Icelandic Krona"
      },
      {
        "title": "1 ISK = 0.047933 TJS",
        "link": "http://www.floatrates.com/isk/tjs/",
        "description": "1 Icelandic Krona = 0.047933 Tajikistan Ruble",
        "pubDate": null,
        "baseCurrency": "ISK",
        "baseName": "Icelandic Krona",
        "targetCurrency": "TJS",
        "targetName": "Tajikistan Ruble",
        "exchangeRate": "0.047933",
        "inverseRate": "20.862293",
        "inverseDescription": "1 Tajikistan Ruble = 20.862293 Icelandic Krona"
      },
      {
        "title": "1 ISK = 19.215503 UZS",
        "link": "http://www.floatrates.com/isk/uzs/",
        "description": "1 Icelandic Krona = 19.215503 Uzbekistan Sum",
        "pubDate": null,
        "baseCurrency": "ISK",
        "baseName": "Icelandic Krona",
        "targetCurrency": "UZS",
        "targetName": "Uzbekistan Sum",
        "exchangeRate": "19.215503",
        "inverseRate": "0.052041",
        "inverseDescription": "1 Uzbekistan Sum = 0.052041 Icelandic Krona"
      },
      {
        "title": "1 ISK = 0.157005 UAH",
        "link": "http://www.floatrates.com/isk/uah/",
        "description": "1 Icelandic Krona = 0.157005 Ukrainian Hryvnia",
        "pubDate": null,
        "baseCurrency": "ISK",
        "baseName": "Icelandic Krona",
        "targetCurrency": "UAH",
        "targetName": "Ukrainian Hryvnia",
        "exchangeRate": "0.157005",
        "inverseRate": "6.369209",
        "inverseDescription": "1 Ukrainian Hryvnia = 6.369209 Icelandic Krona"
      },
      {
        "title": "1 ISK = 0.747182 DZD",
        "link": "http://www.floatrates.com/isk/dzd/",
        "description": "1 Icelandic Krona = 0.747182 Algerian Dinar",
        "pubDate": null,
        "baseCurrency": "ISK",
        "baseName": "Icelandic Krona",
        "targetCurrency": "DZD",
        "targetName": "Algerian Dinar",
        "exchangeRate": "0.747182",
        "inverseRate": "1.338361",
        "inverseDescription": "1 Algerian Dinar = 1.338361 Icelandic Krona"
      },
      {
        "title": "1 ISK = 0.074119 BWP",
        "link": "http://www.floatrates.com/isk/bwp/",
        "description": "1 Icelandic Krona = 0.074119 Botswana Pula",
        "pubDate": null,
        "baseCurrency": "ISK",
        "baseName": "Icelandic Krona",
        "targetCurrency": "BWP",
        "targetName": "Botswana Pula",
        "exchangeRate": "0.074119",
        "inverseRate": "13.491733",
        "inverseDescription": "1 Botswana Pula = 13.491733 Icelandic Krona"
      },
      {
        "title": "1 ISK = 0.010173 BND",
        "link": "http://www.floatrates.com/isk/bnd/",
        "description": "1 Icelandic Krona = 0.010173 Brunei Dollar",
        "pubDate": null,
        "baseCurrency": "ISK",
        "baseName": "Icelandic Krona",
        "targetCurrency": "BND",
        "targetName": "Brunei Dollar",
        "exchangeRate": "0.010173",
        "inverseRate": "98.301654",
        "inverseDescription": "1 Brunei Dollar = 98.301654 Icelandic Krona"
      },
      {
        "title": "1 ISK = 0.002298 KWD",
        "link": "http://www.floatrates.com/isk/kwd/",
        "description": "1 Icelandic Krona = 0.002298 Kuwaiti Dinar",
        "pubDate": null,
        "baseCurrency": "ISK",
        "baseName": "Icelandic Krona",
        "targetCurrency": "KWD",
        "targetName": "Kuwaiti Dinar",
        "exchangeRate": "0.002298",
        "inverseRate": "435.226457",
        "inverseDescription": "1 Kuwaiti Dinar = 435.226457 Icelandic Krona"
      },
      {
        "title": "1 ISK = 0.005404 LYD",
        "link": "http://www.floatrates.com/isk/lyd/",
        "description": "1 Icelandic Krona = 0.005404 Libyan Dinar",
        "pubDate": null,
        "baseCurrency": "ISK",
        "baseName": "Icelandic Krona",
        "targetCurrency": "LYD",
        "targetName": "Libyan Dinar",
        "exchangeRate": "0.005404",
        "inverseRate": "185.040167",
        "inverseDescription": "1 Libyan Dinar = 185.040167 Icelandic Krona"
      },
      {
        "title": "1 ISK = 0.266963 MUR",
        "link": "http://www.floatrates.com/isk/mur/",
        "description": "1 Icelandic Krona = 0.266963 Mauritian Rupee",
        "pubDate": null,
        "baseCurrency": "ISK",
        "baseName": "Icelandic Krona",
        "targetCurrency": "MUR",
        "targetName": "Mauritian Rupee",
        "exchangeRate": "0.266963",
        "inverseRate": "3.745838",
        "inverseDescription": "1 Mauritian Rupee = 3.745838 Icelandic Krona"
      },
      {
        "title": "1 ISK = 0.779320 NPR",
        "link": "http://www.floatrates.com/isk/npr/",
        "description": "1 Icelandic Krona = 0.779320 Nepalese Rupee",
        "pubDate": null,
        "baseCurrency": "ISK",
        "baseName": "Icelandic Krona",
        "targetCurrency": "NPR",
        "targetName": "Nepalese Rupee",
        "exchangeRate": "0.779320",
        "inverseRate": "1.283169",
        "inverseDescription": "1 Nepalese Rupee = 1.283169 Icelandic Krona"
      },
      {
        "title": "1 ISK = 0.002930 OMR",
        "link": "http://www.floatrates.com/isk/omr/",
        "description": "1 Icelandic Krona = 0.002930 Omani Rial",
        "pubDate": null,
        "baseCurrency": "ISK",
        "baseName": "Icelandic Krona",
        "targetCurrency": "OMR",
        "targetName": "Omani Rial",
        "exchangeRate": "0.002930",
        "inverseRate": "341.332999",
        "inverseDescription": "1 Omani Rial = 341.332999 Icelandic Krona"
      },
      {
        "title": "1 ISK = 0.027735 QAR",
        "link": "http://www.floatrates.com/isk/qar/",
        "description": "1 Icelandic Krona = 0.027735 Qatari Rial",
        "pubDate": null,
        "baseCurrency": "ISK",
        "baseName": "Icelandic Krona",
        "targetCurrency": "QAR",
        "targetName": "Qatari Rial",
        "exchangeRate": "0.027735",
        "inverseRate": "36.055642",
        "inverseDescription": "1 Qatari Rial = 36.055642 Icelandic Krona"
      },
      {
        "title": "1 ISK = 0.028573 SAR",
        "link": "http://www.floatrates.com/isk/sar/",
        "description": "1 Icelandic Krona = 0.028573 Saudi Riyal",
        "pubDate": null,
        "baseCurrency": "ISK",
        "baseName": "Icelandic Krona",
        "targetCurrency": "SAR",
        "targetName": "Saudi Riyal",
        "exchangeRate": "0.028573",
        "inverseRate": "34.998010",
        "inverseDescription": "1 Saudi Riyal = 34.998010 Icelandic Krona"
      }
    ]
  }
}